Workbook

Sheet Combined
A1: Respondent ID | B1: Group | C1: Source row | D1: Interviewer | E1: Response timestamp | F1: Age | G1: Age category | H1: Gender | I1: From – State/Province | J1: From – Country | K1: From (State, Country) | L1: Residence – State/Province | M1: Residence – Country | N1: Residence (State, Country) | O1: Q5 How would you define aging? | P1: Q6 Est. % of US population 65+ | Q1: Q6 Estimate (range) | R1: Q7 Greatest challenge facing the aging population | S1: Q8 Challenge to solve in the short term | T1: Q8 Why prioritize it | U1: Q9 Action being taken on this challenge? | V1: Q10 Three things to maintain through life | W1: Q11 What you can do to maintain them | X1: Q12 Description of the three topics | Y1: Personal rank – Reproductive health & longevity | Z1: Personal rank – Democratizing longevity | AA1: Personal rank – AI/ML for aging & health | AB1: Societal rank – Reproductive health & longevity | AC1: Societal rank – Democratizing longevity | AD1: Societal rank – AI/ML for aging & health | AE1: Reason for ranking | AF1: Most exciting topic | AG1: What excites you | AH1: Most concerning topic | AI1: Greatest concern | AJ1: Ethical considerations needed? | AK1: Ethical considerations (details) | AL1: Excited about future of aging research? | AM1: Excitement rating (1–5) | AN1: Excitement comment | AO1: Bioengineers can help? | AP1: Bioengineer role rating (1–5) | AQ1: Bioengineers comment | AR1: Data notes
A2: G1-001 | B2: 1 | C2: 2 | F2: 25 | G2: =IF(F2="","",IF(F2>=Notes!$B$5,"Elderly ("&Notes!$B$5&"+)",IF(F2<=Notes!$B$4,"Student age (≤"&Notes!$B$4&")","Middle-aged ("&(Notes!$B$4+1)&"–"&(Notes!$B$5-1)&")"))) -> Student age (≤29) | H2: Female | I2: Florida | J2: United States | K2: Florida, United States | L2: Maryland | M2: United States | N2: Maryland, United States | O2: Biological and physical changes as a result of time passing! | P2: 35 | Q2: Over 30% | R2: Not enough access to medical care/practitioners. | S2: Promote programs to get more caregivers/nursing home attendants | U2: Programs to sponsor people who plan to be or are caregivers (forgiven college debts), subsidies, free food delivery programs for elderly | V2: My mind, my friends, my ability to move easily | W2: Yoga, reading, going to yoga with friends lol | Y2: 3 | Z2: 1 | AA2: 2 | AB2: 2 | AC2: 1 | AD2: 3 | AG2: As a woman, it is scary to feel pressured to have children when there is little access to good childcare for working women. | AJ2: Yes | AL2: Yes | AO2: Yes
A3: G1-002 | B3: 1 | C3: 3 | F3: 24 | G3: =IF(F3="","",IF(F3>=Notes!$B$5,"Elderly ("&Notes!$B$5&"+)",IF(F3<=Notes!$B$4,"Student age (≤"&Notes!$B$4&")","Middle-aged ("&(Notes!$B$4+1)&"–"&(Notes!$B$5-1)&")"))) -> Student age (≤29) | H3: Female | I3: Pennsylvania | J3: United States | K3: Pennsylvania, United States | L3: Maryland | M3: United States | N3: Maryland, United States | O3: body tissues breaking down, mind gaining experience | P3: 38 | Q3: Over 30% | R3: social support | S3: healthcare resource availability | U3: ehh not really | V3: mental clarity, mental health, mobility | W3: eat good sleep good exercise good protect my relationships | Y3: 2 | Z3: 1 | AA3: 3 | AB3: 3 | AC3: 2 | AD3: 1 | AG3: dementia | AJ3: Yes | AL3: Yes | AO3: Yes
A4: G1-003 | B4: 1 | C4: 4 | F4: 19 | G4: =IF(F4="","",IF(F4>=Notes!$B$5,"Elderly ("&Notes!$B$5&"+)",IF(F4<=Notes!$B$4,"Student age (≤"&Notes!$B$4&")","Middle-aged ("&(Notes!$B$4+1)&"–"&(Notes!$B$5-1)&")"))) -> Student age (≤29) | H4: Female | I4: California | J4: United States | K4: California, United States | L4: Maryland | M4: United States | N4: Maryland, United States | O4: Scary | P4: 10 | Q4: 15% or less | R4: Lack of preventative medicine so diseases and illnesses get caught too late. | S4: Preventative medicine can help prevent consequences that later on can be more costly and painful, if we can figure out a way to encourage more people and to get people more access to said preventative medicine in the short term it will solve a lot of our long term problems. | U4: No, our administration cuts budgets and doesn’t make healthcare more accessible. | V4: Family, physical & mental health | W4: I can keep showing up for people to maintain my community, I can also keep going to check ups and I can pay attention to nutrition and exercise in order to keep my health up. | Y4: 3 | Z4: 3 | AA4: 2 | AB4: 2 | AC4: 1 | AD4: 1 | AG4: I mean the concept of AI taking over our healthcare system is scary but it’s also exciting because it may be a lot more accessible to more people. | AJ4: Yes | AL4: Yes | AO4: Yes | AR4: personal ranks repeat a number (as answered); societal ranks repeat a number (as answered)
A5: G1-004 | B5: 1 | C5: 5 | F5: 21 | G5: =IF(F5="","",IF(F5>=Notes!$B$5,"Elderly ("&Notes!$B$5&"+)",IF(F5<=Notes!$B$4,"Student age (≤"&Notes!$B$4&")","Middle-aged ("&(Notes!$B$4+1)&"–"&(Notes!$B$5-1)&")"))) -> Student age (≤29) | H5: Male | I5: Maryland | J5: United States | K5: Maryland, United States | L5: Maryland | M5: United States | N5: Maryland, United States | O5: telomere degradation | P5: 40 | Q5: Over 30% | R5: Rising technological advances resulting in increased ignorance | S5: Lack of help - basic needs -> foundations of a healthy life | U5: Reformation of nursing homes and communities currently, but unfortunately insufficient | V5: youthful personality, athleticism, and drive | W5: education | Y5: 3 | Z5: 2 | AA5: 1 | AB5: 3 | AC5: 2 | AD5: 1 | AG5: AI predicting modern solutions - both excites me for the future of medicine, but also frightens me for the upcoming consequences | AJ5: Yes | AL5: Yes | AO5: Yes
A6: G1-005 | B6: 1 | C6: 6 | F6: 21 | G6: =IF(F6="","",IF(F6>=Notes!$B$5,"Elderly ("&Notes!$B$5&"+)",IF(F6<=Notes!$B$4,"Student age (≤"&Notes!$B$4&")","Middle-aged ("&(Notes!$B$4+1)&"–"&(Notes!$B$5-1)&")"))) -> Student age (≤29) | H6: Male | I6: Massachusetts | J6: United States | K6: Massachusetts, United States | L6: Maryland | M6: United States | N6: Maryland, United States | O6: Cellular aging | P6: 20 | Q6: 16–20% | R6: Aging with dignity | S6: Demograohic cliff cannot financially support elder cohort | U6: No | V6: Money, movement, mental acuity | W6: Healthy lifestyle | X6: Small tradeoffs now that support longefvkty | Y6: 2 | Z6: 1 | AA6: 3 | AB6: 2 | AC6: 1 | AD6: 3 | AE6: Idk | AG6: Idk | AJ6: Yes | AL6: No | AO6: No
A7: G1-006 | B7: 1 | C7: 7 | F7: 24 | G7: =IF(F7="","",IF(F7>=Notes!$B$5,"Elderly ("&Notes!$B$5&"+)",IF(F7<=Notes!$B$4,"Student age (≤"&Notes!$B$4&")","Middle-aged ("&(Notes!$B$4+1)&"–"&(Notes!$B$5-1)&")"))) -> Student age (≤29) | H7: Male | I7: California | J7: United States | K7: California, United States | L7: California | M7: United States | N7: California, United States | O7: Getting older | P7: 32 | Q7: Over 30% | R7: Dealing with all sorts of age-related diseases/complications | S7: Preventative health so we are proactive instead of reactive | U7: R&D | V7: Vision; Lucidity; Athleticism | W7: Workout; Dont use too many screens; Puzzles | X7: Enjoying life | Y7: 2 | Z7: 1 | AA7: 3 | AB7: 2 | AC7: 1 | AD7: 3 | AE7: I want to be healthy | AG7: Longer healthier lives; AI taking over the world | AJ7: Yes | AL7: Yes | AO7: Yes
A8: G1-007 | B8: 1 | C8: 10 | F8: 20 | G8: =IF(F8="","",IF(F8>=Notes!$B$5,"Elderly ("&Notes!$B$5&"+)",IF(F8<=Notes!$B$4,"Student age (≤"&Notes!$B$4&")","Middle-aged ("&(Notes!$B$4+1)&"–"&(Notes!$B$5-1)&")"))) -> Student age (≤29) | H8: Male | I8: Michigan | J8: United States | K8: Michigan, United States | L8: Maryland | M8: United States | N8: Maryland, United States | O8: Chronologically getting older, or biologically degrading telomeres | P8: 25 | Q8: 21–30% | R8: More and more aging population, but less and less resources to care for them (both monetarily but also human-labor wise) | S8: Find people that are able to give that care at an affordable pace, because without the promise of a worthwhile retirement (age) then people grow less motivated and more focused on trying to make their prime the best it can be. | U8: Make day to day life easier by offering ways for families to take care of their elderly members (leave from work, stipend, etc.) | V8: Physical mobility, cognition (mentally active, lose consciouness and become a shell), keep up with the times (not getting stuck in a mindset) | W8: Keep an open mind, stay healthy be exercising, don’t get complacent about doing things. | X8: Applying modern tech solutions to current problems | Y8: 2 | Z8: 1 | AA8: 3 | AB8: 2 | AC8: 1 | AD8: 3 | AE8: If you can apply broader health impacts across all walks of life, they would most impact people at the current timeframe, but also probably as they grow older they maintain healthier habits and benefits so it’s more lifelong than specific moments. | AG8: Not really exciting, but more of a necessity of things that have to happen if we want our lives to get better. There isn’t enough of a rush or consideration for it in the grand scheme of things currently going on, so much division that there isn’t time to focus on these issues | AJ8: Yes | AL8: Yes | AO8: Yes
A9: G1-008 | B9: 1 | C9: 11 | F9: 20 | G9: =IF(F9="","",IF(F9>=Notes!$B$5,"Elderly ("&Notes!$B$5&"+)",IF(F9<=Notes!$B$4,"Student age (≤"&Notes!$B$4&")","Middle-aged ("&(Notes!$B$4+1)&"–"&(Notes!$B$5-1)&")"))) -> Student age (≤29) | H9: Male | I9: Georgia | J9: United States | K9: Georgia, United States | L9: Maryland | M9: United States | N9: Maryland, United States | O9: Growing older | P9: 12 | Q9: 15% or less | R9: Loneliness | S9: General healthiness | U9: Yes, more mental wellbeing being understood and addressed, people starting to be more active on social media | V9: Health, mental acuity, friends | W9: Maintain good habits, read books, good communication | X9: Three different angles to improving health | Y9: 2 | Z9: 3 | AA9: 1 | AB9: 3 | AC9: 1 | AD9: 2 | AE9: Accessibility to these longevity/health solutions isn’t as important to me as it is for society since I already have access and have a lesser need for them since I am young. I would be more interested in accelerating research in longevity/health. To society, however, accessibility is the most important as everyone deserves a baseline level of access to currently existing science/solutions. | AG9: Iii, it’s newer, and things that leverage ai just excite me personally. We also have a ton of data compiled from years of research. Something that comes to mind is the PDB. The concern though is that it’s newer so there are potential unknown risks of unknown magnitude. | AJ9: Yes | AL9: Yes | AO9: Yes
A10: G1-009 | B10: 1 | C10: 12 | F10: 21 | G10: =IF(F10="","",IF(F10>=Notes!$B$5,"Elderly ("&Notes!$B$5&"+)",IF(F10<=Notes!$B$4,"Student age (≤"&Notes!$B$4&")","Middle-aged ("&(Notes!$B$4+1)&"–"&(Notes!$B$5-1)&")"))) -> Student age (≤29) | H10: Male | I10: Maryland | J10: United States | K10: Maryland, United States | L10: Maryland | M10: United States | N10: Maryland, United States | O10: The process of integrating learned/life experiences throughout one's lifetime. | P10: 30 | Q10: 21–30% | R10: Access to healthcare and socialization | S10: Socialization as issues with healthcare are particularly geared toward a specific group of people while most if not all elderly find it difficult to socialize. | U10: Yes through different social groups or spaces, such as church or even small groups/ clubs. | V10: My memory, cognitive ability, and physical ability. | W10: Maintain my mental and physical routine throughout my lifetime, even as i get older. | X10: (i) Taking action to increase one’s ability to participate in reproductive activities in a healthy way; (ii) Increasing access to healthcare to improve quality of life; (iii) Using AI to inform oneself and others about potential solutions to aging | Y10: 2 | Z10: 1 | AA10: 3 | AB10: 2 | AC10: 3 | AD10: 1 | AE10: I prioritize making health more accessible to others, while I feel as if general society wants to capitalize on the advancements in AI to find an optimal approach to aging. | AG10: ii is most exciting while iii is most concerning. | AJ10: Yes | AL10: Yes | AO10: Yes
A11: G1-010 | B11: 1 | C11: 15 | F11: 20 | G11: =IF(F11="","",IF(F11>=Notes!$B$5,"Elderly ("&Notes!$B$5&"+)",IF(F11<=Notes!$B$4,"Student age (≤"&Notes!$B$4&")","Middle-aged ("&(Notes!$B$4+1)&"–"&(Notes!$B$5-1)&")"))) -> Student age (≤29) | H11: Male | I11: Maryland | J11: United States | K11: Maryland, United States | L11: Maryland | M11: United States | N11: Maryland, United States | O11: Being alive for longer | P11: 32 | Q11: Over 30% | R11: Medical care/retirement funds | S11: Not enough tax money to pay the retirement funds of the aging population. | U11: Increase retirement age or remove social security. | V11: Money; Health; Family | W11: Make sure I make enough money to keep my health and family. | X11: Complex solutions to health | Y11: 1 | Z11: 3 | AA11: 2 | AB11: 1 | AC11: 3 | AD11: 2 | AE11: Health is most important for life. Money is required for health. | AG11: Excited for boosting reproductive health and longevity lets me live longer and feel better as I live longer. I’m afraid that capitalism will commercialize health even more and make it inaccessible to lower middle income individuals. | AJ11: Yes | AL11: Yes | AO11: Yes
A12: G1-011 | B12: 1 | C12: 18 | F12: 22 | G12: =IF(F12="","",IF(F12>=Notes!$B$5,"Elderly ("&Notes!$B$5&"+)",IF(F12<=Notes!$B$4,"Student age (≤"&Notes!$B$4&")","Middle-aged ("&(Notes!$B$4+1)&"–"&(Notes!$B$5-1)&")"))) -> Student age (≤29) | H12: Female | I12: New York | J12: United States | K12: New York, United States | L12: Maryland | M12: United States | N12: Maryland, United States | O12: I think aging is defined as the physical and metabolic/molecular changes that occur within an individual. I believe that there are genetic and environmental factors that can help or hinder a person’s aging rate. I also think that aging is unique to each person because of these factors. | P12: 30 | Q12: 21–30% | R12: maybe disengagement theory- being ostracized from the population which can lead to feeling alienated from dominant society. | S12: I think that the greatest challenge facing our aging population could possibly be them feeling ostracized from the general public, which can affect their mental health and thus cause other health problems. | U12: Not really. I feel like it’s normal for people to do things with their own age group so that might be a reason why I personally don’t see aging populations doing activities that I like to do. | V12: Doing wellness activities (ex. running), reading a lot, being happy. | W12: join groups that are involved in running and living a healthy lifestyle. And hanging out with people who had the same mindset and ideals as me. | X12: do you mean a lot because they define my morals and what my parents and other have taught me to live a fulfilling life. | Y12: 1 | Z12: 2 | AA12: 3 | AB12: 2 | AC12: 1 | AD12: 3 | AE12: I think people will look at things, face value and care about if the solutions are affordable and accessible to them. | AG12: I hope that one day, solutions to aging become accessible to the general public and aren’t expensive and only available to the rich. | AJ12: Yes | AL12: Yes | AO12: Yes
A13: G1-012 | B13: 1 | C13: 19 | F13: 22 | G13: =IF(F13="","",IF(F13>=Notes!$B$5,"Elderly ("&Notes!$B$5&"+)",IF(F13<=Notes!$B$4,"Student age (≤"&Notes!$B$4&")","Middle-aged ("&(Notes!$B$4+1)&"–"&(Notes!$B$5-1)&")"))) -> Student age (≤29) | H13: Male | I13: Texas | J13: United States | K13: Texas, United States | L13: Maryland | M13: United States | N13: Maryland, United States | O13: The passage of time | P13: 25 | Q13: 21–30% | R13: Social security is inadequate for our increasingly aged country | S13: Aged population growth is accelerating while birth rate is declining, having the young take care of the old financially through social security is infeasible, and changes need to be addressed now before the population collapses similar to Korea. | U13: Increase the retirement age. | V13: My physical, mental, and financial health. | W13: Workout and invest heavily | X13: Invest in my future in all aspects of my life. | Y13: 1 | Z13: 2 | AA13: 3 | AB13: 2 | AC13: 1 | AD13: 3 | AE13: I think AI will significantly accelerate aging research which will be helpful for everyone. | AG13: Rich people will live longer and control more. | AJ13: Yes | AL13: No | AO13: Yes
A14: G1-013 | B14: 1 | C14: 20 | F14: 22 | G14: =IF(F14="","",IF(F14>=Notes!$B$5,"Elderly ("&Notes!$B$5&"+)",IF(F14<=Notes!$B$4,"Student age (≤"&Notes!$B$4&")","Middle-aged ("&(Notes!$B$4+1)&"–"&(Notes!$B$5-1)&")"))) -> Student age (≤29) | H14: Male | I14: Maryland | J14: United States | K14: Maryland, United States | L14: California | M14: United States | N14: California, United States | O14: Being alive longer? | P14: 30 | Q14: 21–30% | R14: Healthcare Costs | S14: Healthcare, everyone gets old and more prone to hospital visits. | U14: Honestly no. I know this is unpopular in the largely democratic hopkins space and I am up in the air about how much I truly believe in this idea, I am also kinda ignorant in this topic specifically because I don’t really think or care about the older population very much at this point in my life.; But privatizing advanced medicine isn’t the worst thing in the world. People over 65 already spend a ton of money on healthcare, especially in the last 12 months of life. In the event we spend more money on the elderly what is the end goal? We have a bunch of people who aren’t working and live even longer for what purpose? Especially those who are sick and are living heavily impacted lives. I agree that people who have been working a long time should be rewarded with years of retirement, and that it is truly a matter of luck whether you get to experience those years, but I think it isnt the worst idea in the world for people who have amassed wealth in their life to have better resources for living longer than someone who hasn’t.; To tie a personal story into this. My mom was diagnosed with stage 4 breast cancer about 2 years ago. Shes been doing chemo to minimize and hold out for a vaccine to cure her cancer. Now I don’t actually know how much she is spending on this treatment, but she has amassed 7 figures at least in her 401k (which she can’t even access because shes not 58 or whatever age it is), and she still has money from selling her nice house and moving to Mississippi with my white ass family where cost of living is cheap. All of that is to say, she has had the luxury of fighting this cancer, despite her hating every second, because she made a solid money in her time. Its not like she had generational wealth, she grew up on a farm, and she was the first person in her family to go to graduate school. She just worked really hard to make money and provide for us, another reason why she was able to send me to JHU.; Now obviously nobody is saying that people who have a lot of money shouldnt be allowed to spend their money on their illnesses as an elderly adult. But we both know as people in medicine how expensive it is to get these clinical trials completed and develop the medicine.; I have been working heavily in medicine recently and have learned alot about the grueling process of doing research, developing a drug, and going through the steps of approval for that drug. Its expensive and labor intensive. That costs money, like a lot. So that money is either coming out of our pockets in taxes, or the elderly pockets. I do believe that we should continue spending as a society for the elderly to have care, but there is certainly risk in heavily democratizing care. Do we as a society really benefit from having a bunch of sick old people spending a bunch of money prolonging their life? Honestly, I dont think so. Everybody experiences the loss of their parents, I personally haven’t yet, but I know I will and that reality has been staring me in the face a while. I feel that spending all this money on elderly care just is not the best way forward and I dont see the benefit of spending much more on it. Now I certainly believe the system that needs the most revision is insurance, they make an exuberant amount of money, and this system should exist for people who are unlucky in their younger years and are threatened with the reality that they won’t make it to those retirement years. For people like my mom who have worked hard providing for me and my brother as a single mom and can’t access the 401k money she has saved, I would say insurance and spending exist for them. I understand I am biased and that this logic doesn’t exist for people who aren’t able to save enough money to really retire but that second point is a different story.; I am tired of typing this out I have other things to do, but I did want to provide my perspective, honestly not for you, but for me to be able to get my thoughts on a page and further develop a thought that was sneaking around in the back of my brain and I wanted to understand it.; Alright good luck with this study, and we should probably wish Landon luck because he is about to soend the day at wafflehouse. I will say though good for club basketball because unless he packed on hella weight since I last saw him, he needs it. | V14: Friends, my partner, money | W14: Put extra effort into relationships, make a ton of money | X14: sorry nah | Y14: 1 | Z14: 2 | AA14: 3 | AB14: 1 | AC14: 3 | AD14: 2 | AE14: Healthcare is the most important, AI this AI that whatever, just take viagra tbh; For me I build CNNs and so I care more about AI applications but the other logic is consistent. | AG14: I dont see healthcare changing so its worrying that I will get old and have these issues. I am excited to party with the boys in the retirement home 🎉 | AJ14: Yes | AL14: Yes | AO14: Yes
A15: G1-014 | B15: 1 | C15: 33 | F15: 24 | G15: =IF(F15="","",IF(F15>=Notes!$B$5,"Elderly ("&Notes!$B$5&"+)",IF(F15<=Notes!$B$4,"Student age (≤"&Notes!$B$4&")","Middle-aged ("&(Notes!$B$4+1)&"–"&(Notes!$B$5-1)&")"))) -> Student age (≤29) | H15: Female | I15: Florida | J15: United States | K15: Florida, United States | L15: Maryland | M15: United States | N15: Maryland, United States | O15: The age increasing in number (but != lack of health) | P15: 23 | Q15: 21–30% | R15: Loneliness | S15: Access to healthcare, because everyone deserves equitable healthcare | U15: Medicare has specific initiatives for dementia and other conditions which is good | V15: Health, Energy, Community | W15: Exercise regularly and eat healthy | X15: Capital H Health (not episodic lowercase h health) | Y15: 3 | Z15: 1 | AA15: 2 | AB15: 2 | AC15: 3 | AD15: 1 | AE15: There’s more money going into AI applications and longer reproductive health (IVF, etc) than general healthy aging | AG15: AI/ML pervasively used in everything | AJ15: Yes | AL15: Yes | AO15: Yes
A16: G1-015 | B16: 1 | C16: 34 | F16: 23 | G16: =IF(F16="","",IF(F16>=Notes!$B$5,"Elderly ("&Notes!$B$5&"+)",IF(F16<=Notes!$B$4,"Student age (≤"&Notes!$B$4&")","Middle-aged ("&(Notes!$B$4+1)&"–"&(Notes!$B$5-1)&")"))) -> Student age (≤29) | H16: Male | I16: Florida | J16: United States | K16: Florida, United States | L16: Maryland | M16: United States | N16: Maryland, United States | O16: Levels of Aura | P16: 20 | Q16: 16–20% | R16: Health Care | S16: Lack of health care | U16: More Awareness | V16: 1. Gym Gains; 2. Healthy body; 3. Mobility | W16: Go to Gym | X16: Going to gym and follow routine | Y16: 1 | Z16: 2 | AA16: 3 | AB16: 2 | AC16: 3 | AD16: 1 | AE16: I care about myself rather than training ML models | AG16: The thing that excites me is my determination to get jacked and what scares me is aging | AJ16: No | AL16: Yes | AO16: Yes
A17: G1-016 | B17: 1 | C17: 37 | F17: 22 | G17: =IF(F17="","",IF(F17>=Notes!$B$5,"Elderly ("&Notes!$B$5&"+)",IF(F17<=Notes!$B$4,"Student age (≤"&Notes!$B$4&")","Middle-aged ("&(Notes!$B$4+1)&"–"&(Notes!$B$5-1)&")"))) -> Student age (≤29) | H17: Male | J17: United States | K17: United States | M17: United States | N17: United States | O17: The growth and eventually biological deterioration of the human body and the mind over the course of time | P17: 30 | Q17: 21–30% | R17: Alzheimer’s and chronic illnesses | S17: Healthcare claims | U17: Easier access to healthcare | V17: memory family and health | W17: working out, focus on relationships and mindfulness | X17: Personal growth | Y17: 1 | Z17: 2 | AA17: 3 | AB17: 3 | AC17: 1 | AD17: 2 | AE17: Society vs personal different | AG17: Ai can work i have faith in precision medicine. Frightens is prolly ai too strong and sentient | AJ17: Yes | AL17: Yes | AO17: Yes
A18: G1-017 | B18: 1 | C18: 38 | F18: 24 | G18: =IF(F18="","",IF(F18>=Notes!$B$5,"Elderly ("&Notes!$B$5&"+)",IF(F18<=Notes!$B$4,"Student age (≤"&Notes!$B$4&")","Middle-aged ("&(Notes!$B$4+1)&"–"&(Notes!$B$5-1)&")"))) -> Student age (≤29) | H18: Male | I18: Florida | J18: United States | K18: Florida, United States | L18: Maryland | M18: United States | N18: Maryland, United States | O18: Revolutions around the sun; growth and subsequent decline of physical and mental capacity | P18: 40 | Q18: Over 30% | R18: Disease | S18: Not enough medical workforce to care for aging population | U18: incentives for workforce/nursing | V18: memory, walking, hand mobility | W18: exercise, eat healthy | X18: Take care of your own health | Y18: 3 | Z18: 2 | AA18: 1 | AB18: 3 | AC18: 1 | AD18: 2 | AE18: access is important. we have high population, reproduction might hurt. | AG18: excite: personal medicine. frighten: increased lifespan without health | AJ18: Yes | AL18: Yes | AO18: Yes
A19: G1-018 | B19: 1 | C19: 39 | F19: 22 | G19: =IF(F19="","",IF(F19>=Notes!$B$5,"Elderly ("&Notes!$B$5&"+)",IF(F19<=Notes!$B$4,"Student age (≤"&Notes!$B$4&")","Middle-aged ("&(Notes!$B$4+1)&"–"&(Notes!$B$5-1)&")"))) -> Student age (≤29) | H19: Male | I19: Massachusetts | J19: United States | K19: Massachusetts, United States | L19: Maryland / New Jersey | M19: United States | N19: Maryland / New Jersey, United States | O19: Simply an organism’s forward progression through time. | P19: 15 | Q19: 15% or less | R19: A lot of things; Economically: food insecurity and housing; Biologically: disease, widespread pandemics etc; Epistemologically: AI pollution on the internet and the increasing unverifiability of information; Societally: loneliness; Ecologically: climate change; And much more | S19: No problem worth solving at this scale is solved quickly | U19: Nope. | V19: My mental function; As much athleticism as possible; My penis | W19: Lock in | X19: Read bruh. It’s pretty clear | Y19: 2 | Z19: 1 | AA19: 3 | AB19: 2 | AC19: 3 | AD19: 1 | AE19: Because I think affordable healthcare and actual outcomes matter first more than new discoveries in medicine. More direct impact would easily come from actually applying what we do have currently than from throwing compute at stuff to discover more. That’s important too, but unfortunately society, specifically the tech giants, only care about the frontier and none of the ground level reality of it. | AG19: Nothing scares me.; Everything excited me.; What can I say I’m a chill guy/gal | AJ19: Yes | AL19: Yes | AO19: Yes
A20: G1-019 | B20: 1 | C20: 47 | F20: 26 | G20: =IF(F20="","",IF(F20>=Notes!$B$5,"Elderly ("&Notes!$B$5&"+)",IF(F20<=Notes!$B$4,"Student age (≤"&Notes!$B$4&")","Middle-aged ("&(Notes!$B$4+1)&"–"&(Notes!$B$5-1)&")"))) -> Student age (≤29) | H20: Male | I20: New York | J20: United States | K20: New York, United States | L20: New York | M20: United States | N20: New York, United States | O20: Changes that arise from the passage of time | P20: 15 | Q20: 15% or less | R20: Understanding modern technology and the decline of in-person socialization | S20: In-person socialization and engagement, use of technology. For the former, benefits to health and reducing isolation is very good individually and for society; for the latter, it is important to accommodate and provide services for people that do not freeze out those who are not as familiar, adept, or comfortable with certain technological changes in day-to-day life | U20: Yes. Prioritizing third spaces again, requiring certain provisions in services (physical menus, for example, not just QR codes in restaurants) | V20: -Active lifestyle; -Connection with community and friends; -Travel | W20: Yes. Build foundation and connections, maintain them, prioritize my health throughout my life | X20: Health is wealth | Y20: 2 | Z20: 2 | AA20: 1 | AB20: 3 | AC20: 3 | AD20: 1 | AE20: I am not as concerned individually as society and countries are (and rightfully in many ways) with the problems of aging. I am not in favor of the "break things fast" model of AI development, and although widely used and useful in science, am not sure how important or useful it is or should be in this particular field | AG20: The incredible advancement of science and understanding of biology excites me; the trajectory and reality of widespread AI use without proper regulations and restrictions does not. | AJ20: No | AL20: No | AO20: Yes | AR20: personal ranks repeat a number (as answered); societal ranks repeat a number (as answered)
A21: G1-020 | B21: 1 | C21: 50 | F21: 24 | G21: =IF(F21="","",IF(F21>=Notes!$B$5,"Elderly ("&Notes!$B$5&"+)",IF(F21<=Notes!$B$4,"Student age (≤"&Notes!$B$4&")","Middle-aged ("&(Notes!$B$4+1)&"–"&(Notes!$B$5-1)&")"))) -> Student age (≤29) | H21: Male | I21: Connecticut | J21: United States | K21: Connecticut, United States | L21: Ohio | M21: United States | N21: Ohio, United States | O21: Moving through the years of your life and the experiences that comes with that | P21: 30 | Q21: 21–30% | R21: The ability to understand technology and not be threatened by it or afraid of it | S21: I think offering simpler ways to go about daily tasks that ease in the use of technology would help out | U21: It would be difficult to give everyone access to technology in a short time frame | V21: 1. Ability to connect with people from other generations; 2. Ability to use technology on my own; 3. The desire to still interact with others in the world aside from my immediate family | W21: I can get out and go meet people and build lasting relationships that are important to me | X21: Make an effort to develop your character when you’re young so you are not an outcast when you are old | Y21: 2 | Z21: 2 | AA21: 3 | AB21: 1 | AC21: 1 | AD21: 2 | AE21: I think society does not put an extreme emphasis or importance on ensuring all people are given equal opportunity or the tools to succeed | AG21: Exciting: the development of technology to enhance our day to day life; Frighten: the ability for all to access this technology | AJ21: Yes | AL21: Yes | AO21: Yes | AR21: personal ranks repeat a number (as answered); societal ranks repeat a number (as answered)
A22: G1-021 | B22: 1 | C22: 53 | F22: 28 | G22: =IF(F22="","",IF(F22>=Notes!$B$5,"Elderly ("&Notes!$B$5&"+)",IF(F22<=Notes!$B$4,"Student age (≤"&Notes!$B$4&")","Middle-aged ("&(Notes!$B$4+1)&"–"&(Notes!$B$5-1)&")"))) -> Student age (≤29) | H22: Male | I22: New York | J22: United States | K22: New York, United States | L22: Maryland | M22: United States | N22: Maryland, United States | O22: The generally worsening health and performance outcomes associated with increasing age. | P22: 20 | Q22: 16–20% | R22: Beyond the medical needs that have beset every generation as it ages, the greatest challenge may be the financial burden of providing adequate care to the larger share of Americans who will be retired. | S22: For retired Americans, keeping social security solvent will be important in the next few decades, along with ensuring that social welfare programs cover the medical and financial needs of aging populations more broadly, even as workforce participation may decline due to that aging population. | U22: Likely an increase in the retirement age, but also a larger, more efficient welfare state. | V22: My physical and mental abilities, my health, and my social circle. | W22: Exercise and diet along with preventative care for the first two. For the third, being proactive about socialization | X22: These three things mean my ability to have a fulfilling and active life. | Y22: 1 | Z22: 2 | AA22: 3 | AB22: 2 | AC22: 1 | AD22: 3 | AE22: I believe my socio-economic status means that making longevity science more democratic won't be important to me as an individual, but will be very important to society. The third option reads to me as a means to the first two and so I ranked it lowest. | AG22: I'm excited by the future prospects of longevity science, particularly in how it will let me lead a longer and more fulfilling life. I am concerned by the societal implications of an older society that has not accounted for slower turnover, greater medical costs, etc. | AJ22: Yes | AL22: Yes | AO22: Yes
A23: G1-022 | B23: 1 | C23: 54 | F23: 21 | G23: =IF(F23="","",IF(F23>=Notes!$B$5,"Elderly ("&Notes!$B$5&"+)",IF(F23<=Notes!$B$4,"Student age (≤"&Notes!$B$4&")","Middle-aged ("&(Notes!$B$4+1)&"–"&(Notes!$B$5-1)&")"))) -> Student age (≤29) | H23: Male | I23: California | J23: United States | K23: California, United States | L23: Maryland | M23: United States | N23: Maryland, United States | O23: Body and health deteriorating as you get older | P23: 20 | Q23: 16–20% | R23: Lack of social services | S23: More care centers and promotion of assisted living homes, since many people lack support systems | U23: Opening more facilities | V23: Mobility, independence, energy | W23: Exercise and healthy lifestyle | X23: Be consistent with activity and prioritize longevity over short-term comfort | Y23: 3 | Z23: 3 | AA23: 2 | AB23: 2 | AC23: 1 | AD23: 3 | AE23: I think using modern tech to address these challenges is still a bit premature since we lack the infrastructure to even support them | AG23: Its exciting that advances are being made but frightening that they may not be developed quickly enough for our loved ones and even our own generation | AJ23: Yes | AL23: Yes | AO23: Yes | AR23: personal ranks repeat a number (as answered)
A24: G1-023 | B24: 1 | C24: 55 | F24: 21 | G24: =IF(F24="","",IF(F24>=Notes!$B$5,"Elderly ("&Notes!$B$5&"+)",IF(F24<=Notes!$B$4,"Student age (≤"&Notes!$B$4&")","Middle-aged ("&(Notes!$B$4+1)&"–"&(Notes!$B$5-1)&")"))) -> Student age (≤29) | H24: Male | I24: New Jersey | J24: United States | K24: New Jersey, United States | L24: Maryland | M24: United States | N24: Maryland, United States | O24: Decline of our bodily functions as time passes | P24: 20 | Q24: 16–20% | R24: Too prone to injury | S24: Injuries in the shower should be prioritized because it can be fixed very easily via secure shower mats. | U24: Yes, provide elderly with secure shower mats | V24: Lifting progress, young face, knowledge | W24: Exercise, good sleep, continuing to learn | X24: They mean good healthy both physically and mentally. | Y24: 1 | Z24: 2 | AA24: 3 | AB24: 1 | AC24: 3 | AD24: 2 | AE24: I am a big proponent for AI and think it has huge medical applications. However, I do think that healthcare is too expensive and needs to undergo economic change to become more affordable for Americans. | AG24: Making healthcare affordable will relieve a lot of stress on families but will probably cause another sector's price to spike. | AJ24: Yes | AL24: No | AO24: Yes
A25: G1-024 | B25: 1 | C25: 56 | F25: 18 | G25: =IF(F25="","",IF(F25>=Notes!$B$5,"Elderly ("&Notes!$B$5&"+)",IF(F25<=Notes!$B$4,"Student age (≤"&Notes!$B$4&")","Middle-aged ("&(Notes!$B$4+1)&"–"&(Notes!$B$5-1)&")"))) -> Student age (≤29) | H25: Female | I25: New Jersey | J25: United States | K25: New Jersey, United States | L25: New Jersey | M25: United States | N25: New Jersey, United States | O25: Aging is a developmental part of life that can result in both negative and positive changes in a person | P25: 25 | Q25: 21–30% | R25: Perhaps the lack of willingness to understand them and remember that they are people too, not just things to be taken care of and they once lived the same lives as every young person. | S25: The literacy crisis so that the risk of dementia decreases | U25: Yes, hopefully the government and Department of Education take charge of this matter | V25: My intelligence, my relationships, and my reputation | W25: I can make them a priority and keep making sure I talk to people to learn from them | X25: They shape who I am as a human being. | Y25: 1 | Z25: 2 | AA25: 3 | AB25: 2 | AC25: 1 | AD25: 3 | AE25: I think affordability is one of the foremost issues people have and people are always finding remedies to live longer, which is why I consistently ranked those two as my top two. | AG25: I’m afraid that the sensitive data the AI could contain might be stolen. I’m excited by the thought of AI being able to help cure diseases. | AJ25: Yes | AL25: Yes | AO25: Yes
A26: G1-025 | B26: 1 | C26: 57 | F26: 21 | G26: =IF(F26="","",IF(F26>=Notes!$B$5,"Elderly ("&Notes!$B$5&"+)",IF(F26<=Notes!$B$4,"Student age (≤"&Notes!$B$4&")","Middle-aged ("&(Notes!$B$4+1)&"–"&(Notes!$B$5-1)&")"))) -> Student age (≤29) | H26: Male | I26: California | J26: United States | K26: California, United States | L26: Maryland | M26: United States | N26: Maryland, United States | O26: getting older | P26: 25 | Q26: 21–30% | R26: unable to keep up with technological advancements and health | S26: technological literacy because it is fairly straightforward | U26: policies or pubic awareness campaigns | V26: friends, family, income or job | W26: reminders or continuous check-ups | X26: they are special to me | Y26: 3 | Z26: 1 | AA26: 2 | AB26: 2 | AC26: 1 | AD26: 3 | AE26: reproductive health is important to society | AG26: AI has vast potential | AJ26: Yes | AL26: Yes | AO26: Yes
A27: G1-026 | B27: 1 | C27: 58 | F27: 21 | G27: =IF(F27="","",IF(F27>=Notes!$B$5,"Elderly ("&Notes!$B$5&"+)",IF(F27<=Notes!$B$4,"Student age (≤"&Notes!$B$4&")","Middle-aged ("&(Notes!$B$4+1)&"–"&(Notes!$B$5-1)&")"))) -> Student age (≤29) | H27: Male | I27: Florida | J27: United States | K27: Florida, United States | L27: Virginia | M27: United States | N27: Virginia, United States | O27: decreased quality of life due to mobility and other health issues | P27: 25 | Q27: 21–30% | R27: increased burden on healthcare systems caring for elderly | S27: increased incentives for primary care physicians for the elderly | U27: increase salary for elderly caretakers and primary care of elderly | V27: mobility, independence, health | W27: work out regularly | X27: wellness and health maintenance by taking care of your body | Y27: 3 | Z27: 1 | AA27: 2 | AB27: 2 | AC27: 1 | AD27: 3 | AE27: because for society at a large, immediate interventions that provide the broadest impact are necessary while for individual level, I believe AI innovation is necessary for select individuals to progress and advance the current state of medicine/science | AG27: potential for AI to be used for ill intent | AJ27: Yes | AL27: Yes | AO27: Yes
A28: G1-027 | B28: 1 | C28: 59 | F28: 26 | G28: =IF(F28="","",IF(F28>=Notes!$B$5,"Elderly ("&Notes!$B$5&"+)",IF(F28<=Notes!$B$4,"Student age (≤"&Notes!$B$4&")","Middle-aged ("&(Notes!$B$4+1)&"–"&(Notes!$B$5-1)&")"))) -> Student age (≤29) | H28: Female | J28: Taiwan | K28: Taiwan | L28: Texas | M28: United States | N28: Texas, United States | O28: it’s the cellular, physiological, psychological, and social changes that accrue over time on an individual being | P28: 22 | Q28: 21–30% | R28: shortage of healthcare resources, including nurses, senior homes, home health aid, community spaces. second is social isolation and loneliness. | S28: Care provision. We don’t have a culture of caring for the previous generation like Asian or other countries do. Healthcare isn’t universal, and some older adults run out of resources before they die because now the lifespan is longer and retirement funds are lower. Also, the younger generation bares no obligation to support them, and there is a lack of geriatric care resources. This should be prioritized because the older adult population is exponentially growing, but the resources are not expanding at the same rate. And if we’re lucky, we will all get old so we should all care. | U28: More community and institution level programs for older adult health and longevity (fitness, tech classes, health literacy classes). Some states having policy level plans on aging, like California’s Master Plan on Aging. And some cities like Los Angeles having Departments on Aging that have social work and other services just for older adults. | V28: My memory, having loved ones around me, financial stability | W28: Eat and workout well, don’t drop out of school, and put effort into people. | X28: Wellbeing | Y28: 1 | Z28: 2 | AA28: 3 | AB28: 2 | AC28: 1 | AD28: 3 | AE28: My longevity is the most important to me as an individual because I want to live a long healthy life, and the accessibility of resources contributes to that more greatly than AI does. The accessibility of resources is the most important to society because it can improve the quality of life for older adults on a direct population level. | AG28: It frightens me the amount of states in the US who are not making progress to increase accessibility of older adult resources. It frightens me how little people care. But what excites me is the innovative and interdisciplinary things being implemented in the states that are doing it. Like many OT/PT/RD programs implementing a geriatrics rotation and block in their curriculum. And more nonprofits building social spaces for older adults. | AJ28: Yes | AL28: Yes | AO28: Yes
A29: G1-028 | B29: 1 | C29: 60 | F29: 22 | G29: =IF(F29="","",IF(F29>=Notes!$B$5,"Elderly ("&Notes!$B$5&"+)",IF(F29<=Notes!$B$4,"Student age (≤"&Notes!$B$4&")","Middle-aged ("&(Notes!$B$4+1)&"–"&(Notes!$B$5-1)&")"))) -> Student age (≤29) | H29: Male | I29: Utah | J29: United States | K29: Utah, United States | L29: Maryland | M29: United States | N29: Maryland, United States | O29: Continual process of staying alive | P29: 30 | Q29: 21–30% | R29: Our aging population is increasing due to increased life expectancy, but not enough caregivers. | S29: Promoting elderly care as a profession or family members to take care of aging members. | U29: No | V29: Health, memory, connections | W29: Yes, exercise and social maintenance | X29: maintenance | Y29: 1 | Z29: 3 | AA29: 2 | AB29: 3 | AC29: 1 | AD29: 2 | AE29: Making policies take longer than personal choices, so I ranked on actionable items that I can do to help myself where as I did the reverse order for society to do in order to "keep up" | AG29: I am excited about the advances of medicine that can help me. One thing that scares me is the rapid technological innovation and wondering if AI would have any detrimenting consequences | AJ29: Yes | AL29: Yes | AO29: Yes
A30: G1-029 | B30: 1 | C30: 61 | F30: 22 | G30: =IF(F30="","",IF(F30>=Notes!$B$5,"Elderly ("&Notes!$B$5&"+)",IF(F30<=Notes!$B$4,"Student age (≤"&Notes!$B$4&")","Middle-aged ("&(Notes!$B$4+1)&"–"&(Notes!$B$5-1)&")"))) -> Student age (≤29) | H30: Female | J30: United States | K30: United States | L30: Maryland | M30: United States | N30: Maryland, United States | O30: Wear and tear of the body over time | P30: 30 | Q30: 21–30% | R30: Not enough caretakers | S30: Financial support like Medicare and SSDI, people need to be supported especially at their weakest. So many in poverty at an older age | U30: Yes, some federal programs but not nearly enough | V30: Bone/muscule strength, posture and flexibility, mental stability | W30: Yes, weightlifting | X30: The ability to maintain whats in your control, genetics aside | Y30: 2 | Z30: 3 | AA30: 1 | AB30: 2 | AC30: 3 | AD30: 1 | AE30: Innovations don’t matter if they’re not accessible to those who need it | AG30: Excited about AI creating new innovations, worried that their effects will be limited to those who can afford breakthrough treatments | AJ30: Yes | AL30: Yes | AO30: Yes
A31: G1-030 | B31: 1 | C31: 62 | F31: 23 | G31: =IF(F31="","",IF(F31>=Notes!$B$5,"Elderly ("&Notes!$B$5&"+)",IF(F31<=Notes!$B$4,"Student age (≤"&Notes!$B$4&")","Middle-aged ("&(Notes!$B$4+1)&"–"&(Notes!$B$5-1)&")"))) -> Student age (≤29) | H31: Female | I31: Maryland | J31: United States | K31: Maryland, United States | L31: Maryland | M31: United States | N31: Maryland, United States | O31: The process of growing older over time and changing physically as time moves forward. | P31: 25 | Q31: 21–30% | R31: Healthcare access and cognitive decline | S31: Healthcare access and affordability. The aging population requires more medical care and daily support, which is expensive. It should be prioritized to make healthcare more accessible and affordable because everyone deserves to maintain a good quality of life as they age without the financial burden on themselves or their families. | U31: I am not certain. | V31: Good health, sharp mind, independence | W31: Prioritize my health by staying active and eating healthy. | X31: Being physically and mentally well to enjoy life, make my own decisions, and take care of myself as I age. | Y31: 1 | Z31: 2 | AA31: 3 | AB31: 1 | AC31: 3 | AD31: 2 | AE31: I ranked them for myself this way because it is important for me to maintain longevity and make healthcare more accessible. For society, I think healthcare access is lower on the priority list, while predicting disease is more important. All of these statements are important and should be prioritized to help the aging population. | AG31: It would be amazing to use AI to predict diseases, which excites me. It frightens me that this could create a larger gap in healthcare accessibility because these tools could become extremely expensive. | AJ31: Yes | AL31: Yes | AO31: Yes
A32: G1-031 | B32: 1 | C32: 63 | F32: 25 | G32: =IF(F32="","",IF(F32>=Notes!$B$5,"Elderly ("&Notes!$B$5&"+)",IF(F32<=Notes!$B$4,"Student age (≤"&Notes!$B$4&")","Middle-aged ("&(Notes!$B$4+1)&"–"&(Notes!$B$5-1)&")"))) -> Student age (≤29) | H32: Male | I32: Pennsylvania | J32: United States | K32: Pennsylvania, United States | L32: Maryland | M32: United States | N32: Maryland, United States | O32: The process of getting older and quality of life decreasing as a result. | P32: 35 | Q32: Over 30% | R32: The number of people above the age of 65 is increasing, so access to proper healthcare is a major challenge. | S32: Ensuring that there are proper resources in place to care for the aging population. This should be prioritized because without proper care, QOL will decrease. | U32: Money, resources, geographic limitations. | V32: My physical health, my mental health, and connections to family/friends. | W32: Stay in physical and mental shape, communicate with others, continue to learn and grow. | X32: Foundational principles of a healthy life. | Y32: 2 | Z32: 2 | AA32: 2 | AB32: 1 | AC32: 3 | AD32: 2 | AE32: Longevity is important, but I do not think that is necessarily a goal of everyone unless it is in parallel with QOL increased. Democratizing science should always be a goal so that access to health solutions is not narrowed to the upper class. Applying AI will help and is already happening. | AG32: Excites: Access to new healthcare modalities; Frightens: Access to new healthcare modalities only for those who can afford it | AJ32: Yes | AL32: Yes | AO32: Yes | AR32: personal ranks repeat a number (as answered)
A33: G1-032 | B33: 1 | C33: 65 | F33: 20 | G33: =IF(F33="","",IF(F33>=Notes!$B$5,"Elderly ("&Notes!$B$5&"+)",IF(F33<=Notes!$B$4,"Student age (≤"&Notes!$B$4&")","Middle-aged ("&(Notes!$B$4+1)&"–"&(Notes!$B$5-1)&")"))) -> Student age (≤29) | H33: Male | I33: Massachusetts | J33: United States | K33: Massachusetts, United States | L33: Maryland | M33: United States | N33: Maryland, United States | O33: When the lifespan of your body’s tissues and organs starts coming to an end. | P33: 15 | Q33: 15% or less | R33: cancer | S33: fitness and overall health | U33: more fitness regimes, less processed foods | V33: basketball, health, memory | W33: consistent habits | X33: Everything | Y33: 1 | Z33: 2 | AA33: 3 | AB33: 3 | AC33: 1 | AD33: 2 | AE33: i think the three are all related in some way so the order is varying | AG33: AI excites, AI frightens | AJ33: Yes | AL33: Yes | AO33: Yes
A34: G1-033 | B34: 1 | C34: 66 | F34: 21 | G34: =IF(F34="","",IF(F34>=Notes!$B$5,"Elderly ("&Notes!$B$5&"+)",IF(F34<=Notes!$B$4,"Student age (≤"&Notes!$B$4&")","Middle-aged ("&(Notes!$B$4+1)&"–"&(Notes!$B$5-1)&")"))) -> Student age (≤29) | H34: Male | I34: Maryland | J34: United States | K34: Maryland, United States | L34: Maryland | M34: United States | N34: Maryland, United States | O34: Growing older + the accompanying bio. / phys. changes | P34: 20 | Q34: 16–20% | R34: Aging safely both biologically + socially | S34: Dangerous home design for old people | U34: Not huge movements | V34: Physical activity, good diet, good social connections | W34: Yes | X34: Keeping up to date with housing keeping/health stuff | Y34: 1 | Z34: 2 | AA34: 2 | AB34: 2 | AC34: 2 | AD34: 2 | AE34: I care more about repod. health, but i think society overall cares (not too much) about all 3 the same | AG34: Privacy for AI | AJ34: Yes | AL34: Yes | AO34: Yes | AR34: personal ranks repeat a number (as answered); societal ranks repeat a number (as answered)
A35: G1-034 | B35: 1 | C35: 67 | F35: 21 | G35: =IF(F35="","",IF(F35>=Notes!$B$5,"Elderly ("&Notes!$B$5&"+)",IF(F35<=Notes!$B$4,"Student age (≤"&Notes!$B$4&")","Middle-aged ("&(Notes!$B$4+1)&"–"&(Notes!$B$5-1)&")"))) -> Student age (≤29) | H35: Male | I35: Connecticut | J35: United States | K35: Connecticut, United States | L35: Maryland | M35: United States | N35: Maryland, United States | O35: Getting older / biological age increasing | P35: 23 | Q35: 21–30% | R35: alzheimer's / cognitive diseases | S35: Prioritizing disability awareness and having more accessiblity in public buildings | U35: Rarely | V35: good relationships, good health, purpose | W35: Yes, there are lots of intentional actions I can take for each thing. | X35: The important things for me in life is maintaining close relationships with friends and family, keeping my body health, and having a career/hobbies that fulfills me. | Y35: 2 | Z35: 3 | AA35: 1 | AB35: 2 | AC35: 3 | AD35: 1 | AE35: I think AI can be a double edged sword that leads to more harm than good. | AG35: It's exciting we will get advances in health care that further longevity but the thought of AI corrupting current systems is scary. | AJ35: Yes | AL35: No | AO35: Yes
A36: G1-035 | B36: 1 | C36: 68 | F36: 25 | G36: =IF(F36="","",IF(F36>=Notes!$B$5,"Elderly ("&Notes!$B$5&"+)",IF(F36<=Notes!$B$4,"Student age (≤"&Notes!$B$4&")","Middle-aged ("&(Notes!$B$4+1)&"–"&(Notes!$B$5-1)&")"))) -> Student age (≤29) | H36: Female | I36: Maryland | J36: United States | K36: Maryland, United States | L36: Maryland | M36: United States | N36: Maryland, United States | O36: Natural process that happens through time as you reach the end of your physical life. I think lifestyle things can effect the aging process, like stress, diet, mental/emotional/physical health, and the environment you're in | P36: 20 | Q36: 16–20% | R36: Ability to maintain a good standard of living as they get older (lifestyle and community) | S36: I think overall as people age they become less active and it becomes increasingly difficult for them to get to place like doctors appts, physical therapy, the gym to workout, and staying connected with people as life becomes more isolated. I think short term, getting the aging population to be more active before they become too old can be a immediate short term solution, and more of a preventative measure for the future | U36: I think it has to start before it's too late - it is challenging for middle ages adults to stay healthy and active due to the "hustle culture" and long work hours and commuting, so unhealthy habits (intentially or unintentially) begin before it matters. But emphasizing the importance of health and then also creating systems to help older people have access to appointments and help recover after injuries and help build a community for them | V36: Physical health (ability to walk/lift things), mental health, and spiritual health | W36: Consistency from being young through life until I'm older | X36: Through prioritizing physical, mental, and spiritual health, one can maintain a healthy outlook on life to allow themselves to age smoothly and to be there for the next generations after them. | Y36: 2 | Z36: 1 | AA36: 3 | AB36: 2 | AC36: 3 | AD36: 1 | AE36: For me, I think having things accessible, affordable, and generalizable to all is really important and the only way to help the population as a whole with aging and health. To me if feels like a more root cause approach and helps fix the systems that are on going. For society, I see them as prioritizing the application of machine learning to solve problems with the world with AI and data centers expanding, and there are benefits within that, but I don't think it should be the first importance and takes the human-ness out of aging, disease, adn the individual experience. | AG36: I think it's exciting that there are a lot of advancements contributing to the well-being of individuals and help with longevity and improvement for the heath of individuals and that there is important research to help those that need it. What frightens me is stretching to far away form human nature and relying too much on technology and AI | AJ36: Yes | AL36: Yes | AO36: Yes
A37: G1-036 | B37: 1 | C37: 69 | F37: 22 | G37: =IF(F37="","",IF(F37>=Notes!$B$5,"Elderly ("&Notes!$B$5&"+)",IF(F37<=Notes!$B$4,"Student age (≤"&Notes!$B$4&")","Middle-aged ("&(Notes!$B$4+1)&"–"&(Notes!$B$5-1)&")"))) -> Student age (≤29) | H37: Male | I37: Texas | J37: United States | K37: Texas, United States | L37: Rhode Island | M37: United States | N37: Rhode Island, United States | O37: The components of the body, either individually or collectively, working less well resulting in progressive degeneration of the organism. | P37: 25 | Q37: 21–30% | R37: Lack of primary care doctors and a need for increase in federal funding for specialty residency spots. Lack of knowledge/keeping up with the rapid progression in technology/AI. Self-centered, isolationist culture in America leading to separation of elders from their families and communities. | S37: Increasing primary care providers. | U37: Incentivizing med students to choose primary care specialties by subsidizing med school tuition if they commit to it. | V37: Good sleeping habits, exercising regularly, eating nutritious foods. | W37: Stay disciplined - never stop doing it so it doesn't start seeming like a challenge. | X37: Helping preserve my health proactively. | Y37: 1 | Z37: 2 | AA37: 3 | AB37: 1 | AC37: 2 | AD37: 3 | AE37: 1 encompasses the second and third options, democratizing and AI will go hand in hand. | AG37: N/A | AJ37: Yes | AL37: Yes | AO37: Yes
A38: G1-037 | B38: 1 | C38: 70 | F38: 23 | G38: =IF(F38="","",IF(F38>=Notes!$B$5,"Elderly ("&Notes!$B$5&"+)",IF(F38<=Notes!$B$4,"Student age (≤"&Notes!$B$4&")","Middle-aged ("&(Notes!$B$4+1)&"–"&(Notes!$B$5-1)&")"))) -> Student age (≤29) | H38: Female | I38: Shanghai | J38: China | K38: Shanghai, China | L38: Maryland | M38: United States | N38: Maryland, United States | O38: the number of years since you born | P38: 30 | Q38: 21–30% | R38: loss of physical function and independence, which can lead to a greater need for medical care and financial support | S38: Financial support should be prioritized by creating more programs to help older adults with their financial needs | U38: yes | V38: A clear mind, a healthy body, financial stability | W38: exercise everyday, work hard | X38: I'm not quite sure what this question is asking | Y38: 3 | Z38: 2 | AA38: 1 | AB38: 3 | AC38: 3 | AD38: 3 | AE38: For me, boosting longevity is the most important goal, while the other twos are more important from a societal perspective because they provide practical solutions. | AG38: Boosting longevity is the most exciting to me, but applying machine learning models to this area is a little frightens. | AJ38: Yes | AL38: Yes | AO38: Yes | AR38: societal ranks repeat a number (as answered)
A39: G1-038 | B39: 1 | C39: 71 | F39: 22 | G39: =IF(F39="","",IF(F39>=Notes!$B$5,"Elderly ("&Notes!$B$5&"+)",IF(F39<=Notes!$B$4,"Student age (≤"&Notes!$B$4&")","Middle-aged ("&(Notes!$B$4+1)&"–"&(Notes!$B$5-1)&")"))) -> Student age (≤29) | H39: Female | I39: Beijing | J39: China | K39: Beijing, China | L39: Ontario | M39: Canada | N39: Ontario, Canada | O39: The long term decrease in health, growing older in age, as well as the | P39: 20 | Q39: 16–20% | R39: Social barrier such as Ageism, discrimination and preconceived notion of those who are older. | S39: Raising awareness regarding aging, it should be prioritized as it is a simple first step to eliminate Ageism. | U39: Incorporating these knowledge through educational institutions. | V39: Health, wealth, social connections | W39: Regular exercise, investments, regular contact | X39: The above are things that shows cumulative effect, they will not be wasted. | Y39: 3 | Z39: 1 | AA39: 2 | AB39: 3 | AC39: 1 | AD39: 2 | AE39: Ranked democratizing the knowledge as most important because it kind of relates to what I mentioned above. Health solutions are vital for maintaining longevity. AI is emerging and it would be great to utilize it to benefit the aging population. Reproductive health not so important, there are other technologies like IVF advancing now. | AG39: Frightens about population longevity stretched to too long and resource on earth becomes more scarce. Also looking forward to see how normal population are able to use AI to better their health. | AJ39: Yes | AL39: Yes | AO39: Yes
A40: G1-039 | B40: 1 | C40: 72 | F40: 23 | G40: =IF(F40="","",IF(F40>=Notes!$B$5,"Elderly ("&Notes!$B$5&"+)",IF(F40<=Notes!$B$4,"Student age (≤"&Notes!$B$4&")","Middle-aged ("&(Notes!$B$4+1)&"–"&(Notes!$B$5-1)&")"))) -> Student age (≤29) | H40: Female | J40: China | K40: China | M40: United States | N40: United States | O40: The natural process of body function getting old | P40: 15 | Q40: 15% or less | R40: Lack of services taking care of old people | S40: Maybe the caring system, as the aging population is in a high demand of being cared for. | U40: There might be some new programs for aging group to get care. | V40: 1. Independent living 2. Talking 3. Thinking | W40: More exercise, enough sleep, and more beneficial programs. | X40: Stay healthy and expecting more aging care programs. | Y40: 3 | Z40: 3 | AA40: 3 | AB40: 3 | AC40: 2 | AD40: 1 | AE40: I used to study bioengineering, so I think as AI actively develops, we may use it as an active tool for human health, it is effective and accurate in data, so could be good for producing health models etc. Then democratize it to the public like a chain. I don’t know much about the first choice. | AG40: Excite: apply AI as a prediction tool in human health Frighten: the ethic problem related to AI use | AJ40: Yes | AL40: Yes | AO40: Yes | AR40: personal ranks repeat a number (as answered)
A41: G1-040 | B41: 1 | C41: 73 | F41: 22 | G41: =IF(F41="","",IF(F41>=Notes!$B$5,"Elderly ("&Notes!$B$5&"+)",IF(F41<=Notes!$B$4,"Student age (≤"&Notes!$B$4&")","Middle-aged ("&(Notes!$B$4+1)&"–"&(Notes!$B$5-1)&")"))) -> Student age (≤29) | H41: Female | I41: Wisconsin | J41: United States | K41: Wisconsin, United States | L41: Georgia | M41: United States | N41: Georgia, United States | O41: In humans, it is a biological process that occurs within our cells and organs that results in physical and cognitive changes, eventually leading to death. | P41: 35 | Q41: Over 30% | R41: Accessibility and isolation issues. As people age they are not able to take care of themselves as easily due to not being as mobile and some may not have money to hire caretakers or to live in residential homes, leading to limited ability to leave their homes and do things even at home that they may have been able to do before. | S41: I think that given our falling birth rate, we will soon have a population where the number of retired people far outweigh the number of working ago people. Due to this, we will soon have issues with being able to have enough caretakers for the elderly and there will be a massive overload on the health industry. This should be prioritized because there are steps we can take now to preserve the health and longevity of our aging populations and prepare our health systems for what is to come so that there are no system failures when the day actually comes. | U41: ^^ I don't think there is a perfect solution, but I think there are steps we can take now to lessen future burden. | V41: Cognition, Mobility, Independence | W41: Exercise and staying social | X41: The key to a happy and healthy life? | Y41: 1 | Z41: 3 | AA41: 2 | AB41: 2 | AC41: 3 | AD41: 1 | AE41: I think that | AG41: I think that with AI and healthcare we need to be especially careful about which datasets and populations we are using because they could carry bias that we cannot see. | AJ41: Yes | AL41: Yes | AO41: Yes
A42: G1-041 | B42: 1 | C42: 74 | F42: 24 | G42: =IF(F42="","",IF(F42>=Notes!$B$5,"Elderly ("&Notes!$B$5&"+)",IF(F42<=Notes!$B$4,"Student age (≤"&Notes!$B$4&")","Middle-aged ("&(Notes!$B$4+1)&"–"&(Notes!$B$5-1)&")"))) -> Student age (≤29) | H42: Female | J42: United States | K42: United States | M42: United States | N42: United States | O42: I would define aging as biological changes that denote decline from optimum systems performance. | P42: 36 | Q42: Over 30% | R42: Poor or unavailability of adequate resources such as affordable housing, means of transportation, recreational facilities, etc | S42: Reduce retirement age | U42: No | V42: Health, wealth, family | W42: Yes | X42: Consistent action is key as well as investing in one’s self early | Y42: 2 | Z42: 3 | AA42: 1 | AB42: 2 | AC42: 3 | AD42: 1 | AE42: I see the first two options as synonymous so I ranked them closer together. I think AI can be a supplementary tool to achieving options 1 and 2 which are the main goal. | AG42: One thing that excites me about this is widespread availability to all, getting to live with your aging parents for longer or people who desperately want a child being able to have that.; One thing that frightens me is seeing all this research only serving a certain demographic of people while others do not see any benefit from it. | AJ42: Yes | AL42: Yes | AO42: Yes
A43: G1-042 | B43: 1 | C43: 76 | F43: 27 | G43: =IF(F43="","",IF(F43>=Notes!$B$5,"Elderly ("&Notes!$B$5&"+)",IF(F43<=Notes!$B$4,"Student age (≤"&Notes!$B$4&")","Middle-aged ("&(Notes!$B$4+1)&"–"&(Notes!$B$5-1)&")"))) -> Student age (≤29) | H43: Female | J43: China | K43: China | L43: Wisconsin | M43: United States | N43: Wisconsin, United States | O43: How long since you have born | P43: 20 | Q43: 16–20% | R43: Disease that related with aging | S43: Loss of mobility can be addressed with assistive devices and should be prioritized because it directly affects independence and quality of life. | U43: Yes | V43: Mobility, independence, medical resources | W43: No, no one can predict what happens in the future | X43: Mobility: The ability to move freely. Independence: The ability to live by myself. Medical Resources: Access to necessary healthcare. | Y43: 2 | Z43: 1 | AA43: 3 | AB43: 1 | AC43: 1 | AD43: 2 | AE43: I think boosting reproductive health and longevity is the most important. We should make these benefits accessible to everyone. Applying AI is useful, but I don’t think it should be the main priority. | AG43: Boosting longevity is exciting and but using ai seem a like frightens consider how fast the technology have been developed | AJ43: Yes | AL43: Yes | AO43: Yes | AR43: societal ranks repeat a number (as answered)
A44: G1-043 | B44: 1 | C44: 77 | F44: 22 | G44: =IF(F44="","",IF(F44>=Notes!$B$5,"Elderly ("&Notes!$B$5&"+)",IF(F44<=Notes!$B$4,"Student age (≤"&Notes!$B$4&")","Middle-aged ("&(Notes!$B$4+1)&"–"&(Notes!$B$5-1)&")"))) -> Student age (≤29) | H44: Female | J44: China | K44: China | M44: United States | N44: United States | O44: The natural age increase as time goes by | P44: 15 | Q44: 15% or less | R44: There are fewer people that can work and produce goods, so the price will goes up and the economy will be bad | S44: The new born rate is decreasing these days, so aging issue will become worse later on, we need to increase the new born rate. | U44: Yes | V44: A young mindset so that I won’t be afraid to try new things, the open mindset to always learn new knowledge and accept new technology, and also a passionate heart to take the initiative in trying out stuffs. | W44: I need to start living my life this way from now on so it becomes a habit later on | X44: To start today | Y44: 3 | Z44: 1 | AA44: 2 | AB44: 1 | AC44: 2 | AD44: 3 | AE44: Feels like the society cares about the outcome rather than the approach taken to get to that outcome, AI might be considered as one of the probable approach to that but not the only one. For me personally I want to have access to the tools and care less about the general living situation of other people. | AG44: If I can have access to affordable healthcare, I can see myself living a longer and healthier life, during which I can try out a lot of new things. I am frightened about what it would take us to get to that point, will there be a lot of human experiences involved. | AJ44: Yes | AL44: Yes | AO44: Yes
A45: G1-044 | B45: 1 | C45: 78 | F45: 21 | G45: =IF(F45="","",IF(F45>=Notes!$B$5,"Elderly ("&Notes!$B$5&"+)",IF(F45<=Notes!$B$4,"Student age (≤"&Notes!$B$4&")","Middle-aged ("&(Notes!$B$4+1)&"–"&(Notes!$B$5-1)&")"))) -> Student age (≤29) | H45: Male | J45: China | K45: China | L45: California | M45: United States | N45: California, United States | O45: the biological process of getting older as time past by | P45: 10 | Q45: 15% or less | R45: Health condition as people get older | S45: Health insurance or more healthcare resources. Because the aging population may not have enough opportunities to help with their declining health status. | U45: By passing legislative bills. | V45: Keep exercising, try to eat healthy, and get enough rest. | W45: Meal prep and plan ahead of time | X45: Just good habits to stay healthy | Y45: 3 | Z45: 2 | AA45: 1 | AB45: 1 | AC45: 3 | AD45: 2 | AE45: As a society I think it is more important to provide healthcare resources for the people. But as a individual I think it is more important to take care of your body. | AG45: The potential of how AI can help solve these problems is exciting. What frightens me is how hard to it is to get more healthcare resources or make solutions more accessible and affordable. | AJ45: Yes | AL45: Yes | AO45: Yes
A46: G1-045 | B46: 1 | C46: 79 | F46: 49 | G46: =IF(F46="","",IF(F46>=Notes!$B$5,"Elderly ("&Notes!$B$5&"+)",IF(F46<=Notes!$B$4,"Student age (≤"&Notes!$B$4&")","Middle-aged ("&(Notes!$B$4+1)&"–"&(Notes!$B$5-1)&")"))) -> Middle-aged (30–64) | H46: Female | I46: Shanghai | J46: China | K46: Shanghai, China | L46: Shanghai | M46: China | N46: Shanghai, China | O46: # of years lived | P46: 35 | Q46: Over 30% | R46: Chronic disease | S46: Healthcare system | U46: Yes | V46: Family, health, money | W46: There is no guaranteed way | X46: I mean life is unpredictable, and it’s not a lot you can do | Y46: 1 | Z46: 1 | AA46: 3 | AB46: 1 | AC46: 1 | AD46: 1 | AE46: Personally I think the first and second is most relevant to me | AG46: I think they all sounds exciting | AJ46: Yes | AL46: Yes | AO46: Yes | AR46: personal ranks repeat a number (as answered); societal ranks repeat a number (as answered)
A47: G1-046 | B47: 1 | C47: 80 | F47: 28 | G47: =IF(F47="","",IF(F47>=Notes!$B$5,"Elderly ("&Notes!$B$5&"+)",IF(F47<=Notes!$B$4,"Student age (≤"&Notes!$B$4&")","Middle-aged ("&(Notes!$B$4+1)&"–"&(Notes!$B$5-1)&")"))) -> Student age (≤29) | H47: Male | I47: Oregon | J47: United States | K47: Oregon, United States | L47: Maryland | M47: United States | N47: Maryland, United States | O47: the inevitable march of time | P47: 20 | Q47: 16–20% | R47: erectile dysfunction | S47: getting the channel to work should be prioritized so they can watch TV | U47: calling their grandson seems to be the goto | V47: health, beauty, and age | W47: I've been eating broccoli | X47: Do what your mom told you to do as a kid | Y47: 2 | Z47: 3 | AA47: 1 | AB47: 2 | AC47: 1 | AD47: 3 | AE47: most people care about democratization, and the first encapsulates the third | AG47: insurance companies using AI to be annoying | AJ47: No | AL47: Yes | AO47: Yes
A48: G1-047 | B48: 1 | C48: 81 | F48: 56 | G48: =IF(F48="","",IF(F48>=Notes!$B$5,"Elderly ("&Notes!$B$5&"+)",IF(F48<=Notes!$B$4,"Student age (≤"&Notes!$B$4&")","Middle-aged ("&(Notes!$B$4+1)&"–"&(Notes!$B$5-1)&")"))) -> Middle-aged (30–64) | H48: Female | I48: Pennsylvania | J48: United States | K48: Pennsylvania, United States | L48: Arizona | M48: United States | N48: Arizona, United States | O48: The body not responding to being lived in, the way it used to. | P48: 40 | Q48: Over 30% | R48: Healthcare | S48: Healthcare, because eventually it affects everyone, and our system is garbage. | U48: A lot of talk, less action - and the current administration is making it worse, while claiming they are making it better. | V48: My rights, my sense of humor, my humanity. | W48: Yes, I continue standing up for what's right. | X48: Let's stop treating each other like shit. | Y48: 2 | Z48: 1 | AA48: 3 | AB48: 1 | AC48: 2 | AD48: 3 | AE48: Because society often prioritizes Life of any kind above the quality of that life, and I do not. | AG48: Nothing excites me about these topics right now - it's all frightening. Women are being stripped of their rights to reproductive freedom, and hordes of people are actually dismissing the science behind healthcare. I am disgusted and ashamed of my country right now. | AJ48: Yes | AL48: No | AO48: No
A49: G1-048 | B49: 1 | C49: 82 | F49: 23 | G49: =IF(F49="","",IF(F49>=Notes!$B$5,"Elderly ("&Notes!$B$5&"+)",IF(F49<=Notes!$B$4,"Student age (≤"&Notes!$B$4&")","Middle-aged ("&(Notes!$B$4+1)&"–"&(Notes!$B$5-1)&")"))) -> Student age (≤29) | H49: Female | I49: Texas | J49: United States | K49: Texas, United States | L49: Texas | M49: United States | N49: Texas, United States | O49: The process of maturing physically, cognitively, and emotionally. | P49: 45 | Q49: Over 30% | R49: Rising prices that make it harder to make it off a fixed income. | S49: Financial literacy should be prioritized so individuals can adequately prepare for retirement without having to work in the later stages of life. | U49: Yes; people have a difficult time understanding that the future will come faster than expected, making it harder for people to want to put money aside in the present to benefit them in the future. Also, no amount of financial literacy will impact inflation. | V49: Physical health, memory, and familial relationships | W49: I can exercise regularly, watch my diet closely, and keep updated with research about health trends and newly discovered risk factors. I can also priorice family connection by staying in contact with family even if we move away from each other. | X49: Essential | Y49: 3 | Z49: 1 | AA49: 2 | AB49: 3 | AC49: 1 | AD49: 2 | AE49: If we are going to help with longevity for all individuals, education and accessibility are key. If we are going to use AI, we should utilize it to make more accurate generalizations that can inform health initiatives and benefit individuals from all communities. While reproductive health it’s important, we have enough individuals as it is. We should prioritize the individuals already here who are not receiving adequate care than bringing more individuals into an increasingly under resourced world. | AG49: It excites me that we can utilize technology to improve our health and wellness. I am afraid, however, that like in the past, greed and the pursuit of wealth may prevent certain communities from benefiting from the technology. | AJ49: Yes | AL49: Yes | AO49: Yes
A50: G1-049 | B50: 1 | C50: 83 | F50: 24 | G50: =IF(F50="","",IF(F50>=Notes!$B$5,"Elderly ("&Notes!$B$5&"+)",IF(F50<=Notes!$B$4,"Student age (≤"&Notes!$B$4&")","Middle-aged ("&(Notes!$B$4+1)&"–"&(Notes!$B$5-1)&")"))) -> Student age (≤29) | H50: Male | I50: New York | J50: United States | K50: New York, United States | L50: New York | M50: United States | N50: New York, United States | O50: Aging is the act of getting older. | P50: 40 | Q50: Over 30% | R50: That they won't be able to retire | S50: We need to create stable jobs that people can do for 50 years. Because people keep leaving tehir jobs causing companies to not want to hire people | U50: reate economic policies that allow us to keep hiring and grow. Put laws in place against ai taking jobs. Help small business grow into medium businesses. | V50: My memory, my ability to be active, my energy | W50: Yes. | X50: There are ways to keep yourself those things starting at a young age | Y50: 1 | Z50: 3 | AA50: 2 | AB50: 1 | AC50: 3 | AD50: 2 | AE50: Reproductive health means that people can have more kids. More kids means more schools that keep economic opportunities. More people means more hospitals. | AG50: Right now, old people live suck. People are living longer and having success staying more healthy and happy. | AJ50: No | AL50: Yes | AO50: Yes
A51: G1-050 | B51: 1 | C51: 84 | F51: 21 | G51: =IF(F51="","",IF(F51>=Notes!$B$5,"Elderly ("&Notes!$B$5&"+)",IF(F51<=Notes!$B$4,"Student age (≤"&Notes!$B$4&")","Middle-aged ("&(Notes!$B$4+1)&"–"&(Notes!$B$5-1)&")"))) -> Student age (≤29) | H51: Male | I51: New Jersey | J51: United States | K51: New Jersey, United States | L51: Maryland | M51: United States | N51: Maryland, United States | O51: The depreciation of human abilities as time passes | P51: 20 | Q51: 16–20% | R51: Not exercising | S51: People falling in the shower and breaking their bones, it's an easy fix | U51: Yes, issue free rubber shower mats for good grip | V51: Knowledge, muscle, hair | W51: Study, exercise, eat well | X51: Self-care | Y51: 2 | Z51: 1 | AA51: 3 | AB51: 2 | AC51: 1 | AD51: 3 | AE51: AI is an arms race | AG51: AI being able to recursively train itself (double-edged sword) | AJ51: Yes | AL51: Yes | AO51: Yes
A52: G1-051 | B52: 1 | C52: 85 | F52: 20 | G52: =IF(F52="","",IF(F52>=Notes!$B$5,"Elderly ("&Notes!$B$5&"+)",IF(F52<=Notes!$B$4,"Student age (≤"&Notes!$B$4&")","Middle-aged ("&(Notes!$B$4+1)&"–"&(Notes!$B$5-1)&")"))) -> Student age (≤29) | H52: Male | I52: Maryland | J52: United States | K52: Maryland, United States | L52: Maryland | M52: United States | N52: Maryland, United States | O52: Being over the age of 21 | P52: 20 | Q52: 16–20% | R52: They do not have people to take care of them or support. | S52: Putting more emphasis on supporting elderly. | U52: Time, money, family dynamics. | V52: Health; Money; Time | W52: Putting in the investment early for my health and maintaining it. | X52: Everything | Y52: 3 | Z52: 2 | AA52: 1 | AB52: 1 | AC52: 2 | AD52: 3 | AE52: I ranked them in terms of how important they are to me individually. | AG52: AI is coming to take our jobs and autonomy. | AJ52: Yes | AL52: Yes | AO52: Yes
A53: G1-052 | B53: 1 | C53: 88 | F53: 20 | G53: =IF(F53="","",IF(F53>=Notes!$B$5,"Elderly ("&Notes!$B$5&"+)",IF(F53<=Notes!$B$4,"Student age (≤"&Notes!$B$4&")","Middle-aged ("&(Notes!$B$4+1)&"–"&(Notes!$B$5-1)&")"))) -> Student age (≤29) | H53: Female | I53: New York | J53: United States | K53: New York, United States | L53: New York | M53: United States | N53: New York, United States | O53: getting older in age, having a decline in physical or cellular functions due to age | P53: 20 | Q53: 16–20% | R53: not being able to catch up with the growing technology in this world (e.g., learning how to use an iphone, which may lead to barriers in accessing care and can lead to social isolation especially with how everything relies on technology nowadays) | S53: having the younger population work with the older population on how to use technology, helping to eliminate red tape with certain programs so its easier for the elderly population to access | U53: yes! though i don't feel as if it's a huge priority in our world | V53: self-efficacy, good physical health, friends | W53: exercise/making sure my body is in good shape through healthy habits | X53: not exactly sure what this question means? | Y53: 3 | Z53: 1 | AA53: 2 | AB53: 3 | AC53: 2 | AD53: 1 | AE53: ai is getting really big, i feel like society definitely is prioritizing that right now. i think accessibility is the most important in my opinion. | AG53: one thing that frightens me is the idea of the permanent underclass and how there will be an even bigger wealth inequality (who will get to access these resources like being able to predict the trajectory of a disease? probably the rich). on the other hand, im sure that being able to find solutions for aging/health can alleviate a lot of suffering from families and especially for aging adults dealing with health issues but are still in there 50s and 60s and still have a lot of life yet | AJ53: Yes | AL53: Yes | AO53: Yes
A54: G1-053 | B54: 1 | C54: 89 | F54: 20 | G54: =IF(F54="","",IF(F54>=Notes!$B$5,"Elderly ("&Notes!$B$5&"+)",IF(F54<=Notes!$B$4,"Student age (≤"&Notes!$B$4&")","Middle-aged ("&(Notes!$B$4+1)&"–"&(Notes!$B$5-1)&")"))) -> Student age (≤29) | H54: Male | J54: United States | K54: United States | L54: Maryland | M54: United States | N54: Maryland, United States | O54: The process of growing older | P54: 30 | Q54: 21–30% | R54: Too much isolation amongst older people | S54: Cultural- aging population has less and less relationships with their children and families; resulting in social isolation. By emphasizing the notion of family, people will feel less isolated and less likely to develop diseases like AD and dementia | U54: Eliminate nursing homes/cultural changes in the US | V54: happiness, socialness, good health | W54: Stay connected with friends, live in the present, eat healthy and exercise regularlty | X54: I would describe it as maintaining an active and healthy lifestyle and following the basic measures. | Y54: 1 | Z54: 2 | AA54: 3 | AB54: 1 | AC54: 2 | AD54: 3 | AE54: I think that our priority is too boost health longevity, the AI is just a tool, at the end of the day, people have been followign basic measures to live fulfilling lives. Rather than focusing on AI, we should focus efforts the major causes of these disease in the first place (where >90% of problems originate, ex unhealthy foods, rising obesity, not enough exercise, etc) | AG54: I am excited to help people longer, I am frightened that we will be too hyperfocused on AI and will lose thoughts on the bigger picture. | AJ54: Yes | AL54: Yes | AO54: Yes
A55: G1-054 | B55: 1 | C55: 90 | F55: 59 | G55: =IF(F55="","",IF(F55>=Notes!$B$5,"Elderly ("&Notes!$B$5&"+)",IF(F55<=Notes!$B$4,"Student age (≤"&Notes!$B$4&")","Middle-aged ("&(Notes!$B$4+1)&"–"&(Notes!$B$5-1)&")"))) -> Middle-aged (30–64) | H55: Male | J55: United States | K55: United States | L55: Virginia | M55: United States | N55: Virginia, United States | O55: chronological increase in time and how the body moves along with it. | P55: 25 | Q55: 21–30% | R55: rising chronic condition prevalence | S55: cancer and cardiovascular disease- leading causes of death | U55: emphasis on preventative med | V55: exercise, eat healthy, maintian relationships | W55: be watchful of my intake and stay close to friends and family | X55: I want to stay happy and healthy | Y55: 1 | Z55: 2 | AA55: 3 | AB55: 2 | AC55: 1 | AD55: 3 | AE55: I think that our focus should be on longevity, once we figure this out, then we should focus on the tools and ways to ensure it is equitable. | AG55: excited to learn about AI application in science, fear inequity in outcomes | AJ55: Yes | AL55: Yes | AO55: Yes
A56: G1-055 | B56: 1 | C56: 91 | F56: 54 | G56: =IF(F56="","",IF(F56>=Notes!$B$5,"Elderly ("&Notes!$B$5&"+)",IF(F56<=Notes!$B$4,"Student age (≤"&Notes!$B$4&")","Middle-aged ("&(Notes!$B$4+1)&"–"&(Notes!$B$5-1)&")"))) -> Middle-aged (30–64) | H56: Female | J56: United States | K56: United States | L56: Virginia | M56: United States | N56: Virginia, United States | O56: growing older and your body moving along with time | P56: 20 | Q56: 16–20% | R56: little social cohesion, too much isolation among elders | S56: prioritize good cvd health | U56: watchful of diet, stress and excersie | V56: curiosity, health, positivity | W56: Stay curious about the world around me, have a good diet, and always look at good in people. | X56: This means being kind to those around you and being kind to yourself | Y56: 2 | Z56: 1 | AA56: 3 | AB56: 2 | AC56: 1 | AD56: 3 | AE56: Its important for us to have equitable ways of informing public before we try to improve longevity. The tools (AI) in which we do this are secondary. | AG56: Excited to make people live longer; worried about dangers of AI (security etc) | AJ56: Yes | AL56: Yes | AO56: Yes
A57: G1-056 | B57: 1 | C57: 92 | F57: 21 | G57: =IF(F57="","",IF(F57>=Notes!$B$5,"Elderly ("&Notes!$B$5&"+)",IF(F57<=Notes!$B$4,"Student age (≤"&Notes!$B$4&")","Middle-aged ("&(Notes!$B$4+1)&"–"&(Notes!$B$5-1)&")"))) -> Student age (≤29) | H57: Male | J57: United States | K57: United States | L57: Maryland | M57: United States | N57: Maryland, United States | O57: The process of growing older and seeing physical changes in our body that reflects | P57: 25 | Q57: 21–30% | R57: High rates of cardiovascular disease and cancer | S57: High rates of cardiovascular disease and cancer- Generally these are the number 1 and 2 causes of death worldwide | U57: We should focus more on preventative health. | V57: happiness, discipline and good health | W57: Get involved with the things I love, while being watchful of my diet, exercise, etc. | X57: It means being actively involved in the things I enjoy while also paying attention to my overall health and well-being, including my diet and exercise. | Y57: 1 | Z57: 2 | AA57: 3 | AB57: 1 | AC57: 2 | AD57: 3 | AE57: I think our focus should be on increasing health longevity, and then ensuring equity while optimizing the tools to help us reach these goals. | AG57: I am excited about increasing the age ceiling, but I am worried that we will be hyperfocused on AI without thinking of the bigger problems in society. | AJ57: Yes | AL57: Yes | AO57: Yes
A58: G1-057 | B58: 1 | C58: 93 | F58: 25 | G58: =IF(F58="","",IF(F58>=Notes!$B$5,"Elderly ("&Notes!$B$5&"+)",IF(F58<=Notes!$B$4,"Student age (≤"&Notes!$B$4&")","Middle-aged ("&(Notes!$B$4+1)&"–"&(Notes!$B$5-1)&")"))) -> Student age (≤29) | H58: Male | J58: United States | K58: United States | L58: California | M58: United States | N58: California, United States | O58: Growing older and physiologically changing along with it. | P58: 20 | Q58: 16–20% | R58: Not enough resources to take care of older individuals | S58: Caregiving since there is a shortage of family members who are in touch as well as caregivers in the system in general. This should be prioritized as these people can help the elderly stay healthy | U58: Maintaining family relationships from early on staying in touch as we get older. | V58: good health, happiness, positivity. | W58: Having a good outlook on life and taking care of myself | X58: Having a good outlook on life and taking care of yourself means staying hopeful about the future while actively protecting your physical, mental, and emotional health. | Y58: 1 | Z58: 2 | AA58: 3 | AB58: 1 | AC58: 2 | AD58: 3 | AE58: I think once we figure out the substance to maximizing longevity, then we can ensure that it is equitable and use further tools to optimize it. | AG58: Excited to help my grandparents live longer, worried about secuirty concerns with AI | AJ58: Yes | AL58: Yes | AO58: Yes
A59: G1-058 | B59: 1 | C59: 94 | F59: 22 | G59: =IF(F59="","",IF(F59>=Notes!$B$5,"Elderly ("&Notes!$B$5&"+)",IF(F59<=Notes!$B$4,"Student age (≤"&Notes!$B$4&")","Middle-aged ("&(Notes!$B$4+1)&"–"&(Notes!$B$5-1)&")"))) -> Student age (≤29) | H59: Male | I59: California | J59: United States | K59: California, United States | L59: Maryland | M59: United States | N59: Maryland, United States | O59: The gradual accumulation of physical and biological changes as we get older. | P59: 30 | Q59: 21–30% | R59: Chronic diseases and declining physical function. | S59: Keeping older adults independent should be prioritized because losing independence can greatly affect both quality of life and families. | U59: Yes, through preventative medicine, rehabilitation, and technologies that help people live independently. | V59: Mobility, mental sharpness, and close friendships. | W59: Stay physically active, challenge myself mentally, and make time for other people. | X59: They would allow me to continue doing the things I enjoy without being limited by age. | Y59: 3 | Z59: 2 | AA59: 1 | AB59: 3 | AC59: 1 | AD59: 2 | AE59: AI has a lot of potential to improve how we predict and treat disease, but those advances are most meaningful if people can actually access them. | AG59: I’m excited by the possibility of detecting diseases before symptoms appear, but I worry about AI being used without enough oversight. | AJ59: Yes | AL59: Yes | AO59: Yes
A60: G1-059 | B60: 1 | C60: 95 | F60: 21 | G60: =IF(F60="","",IF(F60>=Notes!$B$5,"Elderly ("&Notes!$B$5&"+)",IF(F60<=Notes!$B$4,"Student age (≤"&Notes!$B$4&")","Middle-aged ("&(Notes!$B$4+1)&"–"&(Notes!$B$5-1)&")"))) -> Student age (≤29) | H60: Male | I60: Virginia | J60: United States | K60: Virginia, United States | L60: Maryland | M60: United States | N60: Maryland, United States | O60: Aging is the process of adapting to changes in your body and abilities as time passes. | P60: 25 | Q60: 21–30% | R60: Maintaining physical function and preventing injuries that can limit independence. | S60: Finding better ways to preserve muscle, strength, and mobility should be prioritized because physical decline can greatly affect a person's independence and quality of life. | U60: Yes, through strength training, injury prevention, and better monitoring of physical health. | V60: Strength, mental sharpness, and the ability to stay engaged with family | W60: stay active in sports and remain curious | X60: I think this means trying to seek outdoors activities when I can and learning new things about the world | Y60: 3 | Z60: 2 | AA60: 1 | AB60: 3 | AC60: 1 | AD60: 2 | AE60: As an athlete, I’m interested in technologies that can improve injury prevention for elders. For society, I think those benefits should be accessible to everyone. | AG60: I am excited for AI to help us live longer, but I don't want us to become overly dependent on it. | AJ60: Yes | AL60: Yes | AO60: Yes
A61: G1-060 | B61: 1 | C61: 96 | F61: 30 | G61: =IF(F61="","",IF(F61>=Notes!$B$5,"Elderly ("&Notes!$B$5&"+)",IF(F61<=Notes!$B$4,"Student age (≤"&Notes!$B$4&")","Middle-aged ("&(Notes!$B$4+1)&"–"&(Notes!$B$5-1)&")"))) -> Middle-aged (30–64) | H61: Male | I61: California | J61: United States | K61: California, United States | L61: Massachusetts | M61: United States | N61: Massachusetts, United States | O61: Aging is the gradual decline in physiological reserve that increases vulnerability to disease. | P61: 20 | Q61: 16–20% | R61: The increasing burden of chronic disease and disability. | S61: Preventing loss of functional independence, because preserving quality of life should be as important as extending lifespan. | U61: Earlier detection of disease, preventive medicine, exercise, and better management of chronic conditions. | V61: Cognition, mobility, and independence. | W61: Regular exercise, a healthy diet, preventive screening, cognitive engagement, and maintaining social connections. | X61: They allow a person to remain healthy, functional, and engaged in life rather than simply living longer. | Y61: 3 | Z61: 1 | AA61: 2 | AB61: 3 | AC61: 1 | AD61: 2 | AE61: Scientific advances have limited impact if they are inaccessible. I would prioritize making effective interventions broadly available, with AI serving as a tool to improve prevention and personalized care. | AG61: I am excited by the potential of AI to identify disease earlier and personalize prevention. I am concerned that unequal access to these technologies could worsen existing health disparities. | AJ61: Yes | AL61: Yes | AO61: Yes
A62: G1-061 | B62: 1 | C62: 97 | F62: 22 | G62: =IF(F62="","",IF(F62>=Notes!$B$5,"Elderly ("&Notes!$B$5&"+)",IF(F62<=Notes!$B$4,"Student age (≤"&Notes!$B$4&")","Middle-aged ("&(Notes!$B$4+1)&"–"&(Notes!$B$5-1)&")"))) -> Student age (≤29) | H62: Male | I62: Virginia | J62: United States | K62: Virginia, United States | L62: Virginia | M62: United States | N62: Virginia, United States | O62: A lifelong process influenced by both our biology and the communities we live in | P62: 24 | Q62: 21–30% | R62: Social isolation and unequal access to healthcare and community resources. | S62: Keeping older adults connected to their communities, because isolation can affect both physical and mental well-being. | U62: Yes, via community programs, transportation services, senior centers, and more accessible preventive healthcare. | V62: Mobility, social connections, and independence. | W62: Stay active, build strong relationships, and remain involved in my community. | X62: They allow people to remain healthy, connected, and involved in the communities they care about. | Y62: 3 | Z62: 1 | AA62: 2 | AB62: 2 | AC62: 1 | AD62: 3 | AE62: I think the biggest benefit comes from making health advances available across different communities, especially those that have historically had fewer resources. | AG62: I am excited about using AI to identify health risks earlier. I worry that communities with fewer resources could be left behind as new technologies develop. | AJ62: Yes | AL62: Yes | AO62: Yes
A63: G1-062 | B63: 1 | C63: 98 | F63: 23 | G63: =IF(F63="","",IF(F63>=Notes!$B$5,"Elderly ("&Notes!$B$5&"+)",IF(F63<=Notes!$B$4,"Student age (≤"&Notes!$B$4&")","Middle-aged ("&(Notes!$B$4+1)&"–"&(Notes!$B$5-1)&")"))) -> Student age (≤29) | H63: Male | I63: Virginia | J63: United States | K63: Virginia, United States | L63: Virginia | M63: United States | N63: Virginia, United States | O63: Aging is a normal part of life that is strongly influenced by the conditions in which people live. | P63: 15 | Q63: 15% or less | R63: Helping people age safely and independently, especially in underserved communities. | S63: Improving access to preventive and primary care, because many problems can be managed more effectively when caught early. | U63: Expanding neighborhood health programs, community outreach, transportation options, and health education. | V63: My health, relationships, and ability to be active. | W63: Stay physically active, make time for family and friends, and regularly monitor my health. | X63: They are the foundation for being able to participate fully in everyday life. | Y63: 3 | Z63: 1 | AA63: 2 | AB63: 3 | AC63: 1 | AD63: 2 | AE63: I would prioritize solutions that can improve health across entire populations rather than only helping people who have access to specialized care. | AG63: I am excited by the possibility of technology helping communities prevent disease earlier. I am concerned that new advances may not reach rural or underserved populations equally. | AJ63: Yes | AL63: Yes | AO63: Yes
A64: G1-063 | B64: 1 | C64: 99 | F64: 20 | G64: =IF(F64="","",IF(F64>=Notes!$B$5,"Elderly ("&Notes!$B$5&"+)",IF(F64<=Notes!$B$4,"Student age (≤"&Notes!$B$4&")","Middle-aged ("&(Notes!$B$4+1)&"–"&(Notes!$B$5-1)&")"))) -> Student age (≤29) | H64: Female | J64: Hungary | K64: Hungary | L64: New York | M64: United States | N64: New York, United States | O64: Telomeres shortening | P64: 70 | Q64: Over 30% | R64: Universal Healthcare, GMOs, and Cancer | S64: I believe the greatest challenge facing our aging population is access to affordable, comprehensive healthcare. Many diseases and conditions can be treated or managed, but financial barriers can prevent older adults from receiving timely care. Prioritizing universal healthcare would help them access treatment, maintain their independence, and improve their quality of life. | U64: I would support expanding affordable healthcare coverage, lowering out-of-pocket costs, and making preventive care more accessible to older adults. | V64: I would like to maintain my physical and mental health, my independence, and meaningful relationships with the people I care about. | W64: I can work toward these goals by staying active, caring for my mental well-being, attending regular checkups, and making time for relationships. Continuing to learn and planning financially could also help me preserve my independence. | X64: Together, these mean being able to live on my own terms, enjoy life, and stay connected to the people I love as I age. | Y64: 1 | Z64: 2 | AA64: 3 | AB64: 2 | AC64: 1 | AD64: 3 | AE64: I ranked reproductive health and longevity first personally because I value maintaining my health and having choices about my future as I age. For society, I placed accessible and affordable health solutions first because everyone should have the opportunity to benefit from scientific advances. I ranked AI third because I see it as a tool to support these goals, with its value depending on how effectively and fairly it is used. | AG64: I’m excited by AI’s potential to identify disease risks earlier and help personalize care. What frightens me is the possibility that biased data or unequal access could cause these tools to reinforce existing healthcare inequalities. | AJ64: Yes | AL64: Yes | AO64: Yes
A65: G1-064 | B65: 1 | C65: 100 | F65: 22 | G65: =IF(F65="","",IF(F65>=Notes!$B$5,"Elderly ("&Notes!$B$5&"+)",IF(F65<=Notes!$B$4,"Student age (≤"&Notes!$B$4&")","Middle-aged ("&(Notes!$B$4+1)&"–"&(Notes!$B$5-1)&")"))) -> Student age (≤29) | H65: Male | I65: California | J65: United States | K65: California, United States | L65: Maryland | M65: United States | N65: Maryland, United States | O65: Progressive loss of function over time | P65: 35 | Q65: Over 30% | R65: A lack of young people | S65: we do not have infrastructure to support them | U65: better governmental policy | V65: memory, mobility, health | W65: excercising daily, maintaining a good diet, using my brain every day | X65: What they mean | Y65: 1 | Z65: 2 | AA65: 3 | AB65: 1 | AC65: 2 | AD65: 3 | AE65: I think that makes the most sense to me | AG65: Excites: we can live longer and heathier; Frightens: we might have to work longer as the government will increase the retirement age | AJ65: Yes | AL65: Yes | AO65: Yes
A66: G1-065 | B66: 1 | C66: 102 | F66: 27 | G66: =IF(F66="","",IF(F66>=Notes!$B$5,"Elderly ("&Notes!$B$5&"+)",IF(F66<=Notes!$B$4,"Student age (≤"&Notes!$B$4&")","Middle-aged ("&(Notes!$B$4+1)&"–"&(Notes!$B$5-1)&")"))) -> Student age (≤29) | H66: Male | I66: Virginia | J66: United States | K66: Virginia, United States | L66: Virginia | M66: United States | N66: Virginia, United States | O66: A natural process where the body gradually changes and becomes more susceptible to disease. | P66: 18 | Q66: 16–20% | R66: Managing chronic disease while maintaining quality of life. | S66: Earlier detection of age-related diseases, because identifying problems sooner can lead to better outcomes. | U66: Yes via better screening, preventative care, and predictive health technologies. | V66: Physical health, cognitive ability, and independence. | W66: Exercise, stay mentally active, eat well, and keep up with regular healthcare. | X66: They allow me to remain capable of making decisions and doing the things I enjoy. | Y66: 3 | Z66: 2 | AA66: 1 | AB66: 3 | AC66: 1 | AD66: 2 | AE66: AI could help us detect and manage disease earlier, but those advances are most meaningful if they can eventually benefit a broad population. | AG66: I am excited by AI's potential to predict health risks before symptoms appear. I worry about inaccurate models, biased data, and patient privacy. | AJ66: Yes | AL66: Yes | AO66: Yes
A67: G1-066 | B67: 1 | C67: 103 | F67: 24 | G67: =IF(F67="","",IF(F67>=Notes!$B$5,"Elderly ("&Notes!$B$5&"+)",IF(F67<=Notes!$B$4,"Student age (≤"&Notes!$B$4&")","Middle-aged ("&(Notes!$B$4+1)&"–"&(Notes!$B$5-1)&")"))) -> Student age (≤29) | H67: Male | I67: Virginia | J67: United States | K67: Virginia, United States | L67: Virginia | M67: United States | N67: Virginia, United States | O67: A complex biological process that changes how the body responds to stress, disease, and its environment. | P67: 23 | Q67: 21–30% | R67: Understanding why people age so differently and predicting who is most at risk for disease or disability. | S67: Using existing health data more effectively to identify preventable risks before they become major problems. | U67: Yes, by integrating clinical records, wearable data, imaging, and other health information to build better risk models. | V67: cognitive function, physical mobility, and independence. | W67: Exercise, stay intellectually engaged, maintain good habits, and monitor changes in my health. | X67: They are the abilities that let someone remain active and make their own choices as they get older. | Y67: 3 | Z67: 2 | AA67: 1 | AB67: 3 | AC67: 1 | AD67: 2 | AE67: AI has the potential to find patterns that are difficult for humans to identify, but the resulting tools need to be affordable and useful across different populations. | AG67: I am excited by the possibility of building personalized models of health and aging. I am concerned about models making confident predictions from incomplete or biased data. | AJ67: Yes | AL67: Yes | AO67: Yes
A68: G1-067 | B68: 1 | C68: 104 | F68: 22 | G68: =IF(F68="","",IF(F68>=Notes!$B$5,"Elderly ("&Notes!$B$5&"+)",IF(F68<=Notes!$B$4,"Student age (≤"&Notes!$B$4&")","Middle-aged ("&(Notes!$B$4+1)&"–"&(Notes!$B$5-1)&")"))) -> Student age (≤29) | H68: Male | I68: California | J68: United States | K68: California, United States | L68: California | M68: United States | N68: California, United States | O68: A natural part of life that brings physical, cognitive, and social changes over time. | P68: 22 | Q68: 21–30% | R68: Preventing chronic disease while helping people maintain their independence. | S68: Improving preventive care, because catching health problems early can help people stay healthier for longer. | U68: More accessible screenings, community health programs, and better patient education. | V68: My health, independence, and relationships. | W68: Exercise, eat well, stay socially connected, and keep up with preventive care. | X68: They allow me to stay active, connected, and able to make my own choices. | Y68: 3 | Z68: 1 | AA68: 2 | AB68: 3 | AC68: 1 | AD68: 2 | AE68: As someone interested in medicine, I think advances are most meaningful when they improve outcomes and are accessible to patients from different backgrounds. | AG68: I am excited by the possibility of helping people live healthier for longer. I worry that advances in longevity could become inaccessible to many patients. | AJ68: Yes | AL68: Yes | AO68: Yes
A69: G1-068 | B69: 1 | C69: 105 | F69: 23 | G69: =IF(F69="","",IF(F69>=Notes!$B$5,"Elderly ("&Notes!$B$5&"+)",IF(F69<=Notes!$B$4,"Student age (≤"&Notes!$B$4&")","Middle-aged ("&(Notes!$B$4+1)&"–"&(Notes!$B$5-1)&")"))) -> Student age (≤29) | H69: Female | I69: California | J69: United States | K69: California, United States | L69: Maryland | M69: United States | N69: Maryland, United States | O69: A lifelong process that affects the body, mind, and ability to interact with the world around us. | P69: 15 | Q69: 15% or less | R69: Maintaining quality of life as people experience more health conditions and physical limitations. | S69: Better support for managing chronic conditions, because many older adults live with multiple conditions at once. | U69: Improving primary care, coordinating between healthcare providers, and helping patients better understand their treatment plans. | V69: My physical abilities, mental well-being, and close relationships. | W69: Stay active, prioritize my mental health, maintain friendships, and get regular medical checkups. | X69: They help me remain independent while continuing to enjoy meaningful experiences with the | Y69: 2 | Z69: 1 | AA69: 3 | AB69: 3 | AC69: 1 | AD69: 2 | AE69: I think healthcare advances should ultimately focus on helping people live healthier lives and making those benefits available to as many patients as possible. | AG69: I am excited about finding better ways to prevent age-related disease. I am concerned that focusing too much on lifespan could distract from quality of life. | AJ69: Yes | AL69: Yes | AO69: Yes
A70: G1-069 | B70: 1 | C70: 106 | F70: 48 | G70: =IF(F70="","",IF(F70>=Notes!$B$5,"Elderly ("&Notes!$B$5&"+)",IF(F70<=Notes!$B$4,"Student age (≤"&Notes!$B$4&")","Middle-aged ("&(Notes!$B$4+1)&"–"&(Notes!$B$5-1)&")"))) -> Middle-aged (30–64) | H70: Male | I70: Virginia | J70: United States | K70: Virginia, United States | L70: Virginia | M70: United States | N70: Virginia, United States | O70: A gradual decline in physiologic reserve that affects how well the body responds to illness and stress. | P70: 20 | Q70: 16–20% | R70: Managing multiple chronic conditions while preserving function and independence. | S70: Improving preventive and primary care for older adults, because early intervention can prevent complications and preserve function. | U70: Better coordination between providers, routine screening, medication review, and stronger preventive care. | V70: Mobility, cognition, and independence. | W70: Regular physical activity, good nutrition, preventive care, and staying socially and intellectually engaged. | X70: They are the foundation for maintaining function and having control over how I live my life. | Y70: 3 | Z70: 1 | AA70: 2 | AB70: 3 | AC70: 1 | AD70: 2 | AE70: From a clinical perspective, extending lifespan is most valuable when it also preserves function and quality of life. Advances should therefore be both effective and broadly accessible. | AG70: I am excited about shifting medicine toward earlier prevention of age-related disease. I am concerned about interventions that extend lifespan without meaningfully improving healthspan. | AJ70: Yes | AL70: Yes | AO70: Yes
A71: G1-070 | B71: 1 | C71: 107 | F71: 45 | G71: =IF(F71="","",IF(F71>=Notes!$B$5,"Elderly ("&Notes!$B$5&"+)",IF(F71<=Notes!$B$4,"Student age (≤"&Notes!$B$4&")","Middle-aged ("&(Notes!$B$4+1)&"–"&(Notes!$B$5-1)&")"))) -> Middle-aged (30–64) | H71: Female | I71: Massachusetts | J71: United States | K71: Massachusetts, United States | L71: Virginia | M71: United States | N71: Virginia, United States | O71: A gradual change in physical and cognitive function over time. | P71: 20 | Q71: 16–20% | R71: Maintaining independence. | S71: Preventing avoidable disability and keeping people functional. | U71: Stronger preventive care and early intervention. | V71: Mobility, cognition, and relationships. | W71: Exercise, stay engaged, and get regular checkups. | X71: Being able to live independently and meaningfully. | Y71: 3 | Z71: 1 | AA71: 2 | AB71: 3 | AC71: 1 | AD71: 2 | AE71: Longevity advances matter most when patients can actually access them. | AG71: Excited by better prevention; concerned about unequal access. | AJ71: Yes | AL71: Yes | AO71: Yes
A72: G1-071 | B72: 1 | C72: 108 | F72: 50 | G72: =IF(F72="","",IF(F72>=Notes!$B$5,"Elderly ("&Notes!$B$5&"+)",IF(F72<=Notes!$B$4,"Student age (≤"&Notes!$B$4&")","Middle-aged ("&(Notes!$B$4+1)&"–"&(Notes!$B$5-1)&")"))) -> Middle-aged (30–64) | H72: Female | I72: Virginia | J72: United States | K72: Virginia, United States | L72: Virginia | M72: United States | N72: Virginia, United States | O72: Accumulated biological change. | P72: 20 | Q72: 16–20% | R72: Frailty and chronic illness. | S72: Fall prevention and mobility. | U72: Exercise programs and home safety. | V72: Strength, memory, independence. | W72: Stay active and get preventive care. | X72: Living well without unnecessary limitations. | Y72: 3 | Z72: 2 | AA72: 1 | AB72: 3 | AC72: 1 | AD72: 2 | AE72: Access and impact matter most. | AG72: Better prediction; data privacy. | AJ72: Yes | AL72: Yes | AO72: Yes
A73: G1-072 | B73: 1 | C73: 109 | F73: 22 | G73: =IF(F73="","",IF(F73>=Notes!$B$5,"Elderly ("&Notes!$B$5&"+)",IF(F73<=Notes!$B$4,"Student age (≤"&Notes!$B$4&")","Middle-aged ("&(Notes!$B$4+1)&"–"&(Notes!$B$5-1)&")"))) -> Student age (≤29) | H73: Male | I73: Virginia | J73: United States | K73: Virginia, United States | L73: Virginia | M73: United States | N73: Virginia, United States | O73: A lifelong change in health and resilience. | P73: 20 | Q73: 16–20% | R73: Social isolation. | S73: Address loneliness early. | U73: Community programs and screening. | V73: Relationships, mobility, purpose. | W73: Stay active connected etc | X73: Having reasons to stay engaged in life. | Y73: 3 | Z73: 1 | AA73: 2 | AB73: 2 | AC73: 1 | AD73: 3 | AE73: Health should be accessible and holistic | AG73: Personalized care; overreliance on technology. | AJ73: Yes | AL73: Yes | AO73: Yes
A74: G1-073 | B74: 1 | C74: 110 | F74: 23 | G74: =IF(F74="","",IF(F74>=Notes!$B$5,"Elderly ("&Notes!$B$5&"+)",IF(F74<=Notes!$B$4,"Student age (≤"&Notes!$B$4&")","Middle-aged ("&(Notes!$B$4+1)&"–"&(Notes!$B$5-1)&")"))) -> Student age (≤29) | H74: Male | I74: Virginia | J74: United States | K74: Virginia, United States | L74: Virginia | M74: United States | N74: Virginia, United States | O74: Getting older over time | P74: 20 | Q74: 16–20% | R74: Preventing disability. | S74: Improving preventive care, since small interventions can make a major difference later in life. | U74: Earlier screening and better chronic disease management. | V74: Mobility, cognition, and independence. | W74: Exercise regularly, eat well, stay mentally active, and keep up with routine care. | X74: They allow people to remain active and make their own choices as they age. | Y74: 3 | Z74: 1 | AA74: 2 | AB74: 3 | AC74: 1 | AD74: 2 | AE74: The greatest advances are those that improve health without creating another divide between people who can afford care and those who cannot. | AG74: Excited by better disease prevention; concerned about overtreatment and unnecessary medicalization of aging. | AJ74: Yes | AL74: Yes | AO74: Yes
A75: G1-074 | B75: 1 | C75: 111 | F75: 22 | G75: =IF(F75="","",IF(F75>=Notes!$B$5,"Elderly ("&Notes!$B$5&"+)",IF(F75<=Notes!$B$4,"Student age (≤"&Notes!$B$4&")","Middle-aged ("&(Notes!$B$4+1)&"–"&(Notes!$B$5-1)&")"))) -> Student age (≤29) | H75: Male | I75: Virginia | J75: United States | K75: Virginia, United States | L75: Virginia | M75: United States | N75: Virginia, United States | O75: Getting older while adapting to changes in your body and life. | P75: 25 | Q75: 21–30% | R75: losing independece | S75: Helping people stay active and connected for as long as possible. | U75: More support for exercise, nutrition, and social connection. | V75: My health, family, and independence. | W75: Take care of myself and make time for the people I love. | X75: Being healthy enough to enjoy life with the people who matter to me. | Y75: 3 | Z75: 1 | AA75: 2 | AB75: 2 | AC75: 1 | AD75: 3 | AE75: Living longer only matters if people can actually enjoy those extra years. | AG75: Excited about healthier aging; worried about losing the human side of medicine. | AJ75: Yes | AL75: Yes | AO75: Yes
A76: G1-075 | B76: 1 | C76: 112 | F76: 23 | G76: =IF(F76="","",IF(F76>=Notes!$B$5,"Elderly ("&Notes!$B$5&"+)",IF(F76<=Notes!$B$4,"Student age (≤"&Notes!$B$4&")","Middle-aged ("&(Notes!$B$4+1)&"–"&(Notes!$B$5-1)&")"))) -> Student age (≤29) | H76: Female | I76: Illinois | J76: United States | K76: Illinois, United States | L76: Illinois | M76: United States | N76: Illinois, United States | O76: Being in 60s | P76: 20 | Q76: 16–20% | R76: Probably healthcare | S76: Definitely affordable healthcare | U76: lower prescription drug costs and making long term care more affordable and accessible | V76: My health, my wealth, my support system | W76: Preventative care, investment, and being involved with my community. | X76: Preparing for a future with integral resources | Y76: 2 | Z76: 1 | AA76: 3 | AB76: 2 | AC76: 1 | AD76: 3 | AE76: I do think that accessibility of healthcare is the primary hindrance for healthcare in this country. I do think research is also equally important. AI can definitely help, but if it doesn't reach people to the extent required it won't be effective on a bigger scale | AG76: I'm excited that people will be able to live longer and healthier lives but I constantly worry if the future is going to be hospitable in terms of wealth, the environment and healthcare options we are preparing for. | AJ76: Yes | AL76: Yes | AO76: Yes
A77: G2-001 | B77: 2 | C77: 9 | F77: 20 | G77: =IF(F77="","",IF(F77>=Notes!$B$5,"Elderly ("&Notes!$B$5&"+)",IF(F77<=Notes!$B$4,"Student age (≤"&Notes!$B$4&")","Middle-aged ("&(Notes!$B$4+1)&"–"&(Notes!$B$5-1)&")"))) -> Student age (≤29) | H77: Male | I77: Tennessee | J77: United States | K77: Tennessee, United States | L77: Tennessee | M77: United States | N77: Tennessee, United States | O77: The process where the body slowly deteriorates due to ware in cells and genome | P77: 40 | Q77: Over 30% | R77: Issues with connecting to a rapidly changing social and professional environmen. | S77: I believe the insurance commuting elder fraud should be fixed as it is damaging and leaves elders very vulnerable. | U77: No | V77: Memory, connections, athleticism | W77: I excersizes to stay healthy and fit. | X77: 1-ensuring the human body functions properly with proper health. 2-fixing the current system to promote long-time health and success. 3-facilitating a streamlined process in aging research | Y77: 1 | Z77: 2 | AA77: 3 | AB77: 3 | AC77: 1 | AD77: 2 | AE77: I believe health is most important personally, but society values productiveness over personal health. | AF77: AI/ML for aging & health | AH77: Democratizing longevity (access) | AJ77: Yes | AK77: Ensuring safe research when using human subjects | AL77: Yes | AO77: Yes
A78: G2-002 | B78: 2 | C78: 10 | F78: 19 | G78: =IF(F78="","",IF(F78>=Notes!$B$5,"Elderly ("&Notes!$B$5&"+)",IF(F78<=Notes!$B$4,"Student age (≤"&Notes!$B$4&")","Middle-aged ("&(Notes!$B$4+1)&"–"&(Notes!$B$5-1)&")"))) -> Student age (≤29) | H78: Male | I78: Arkansas | J78: United States | K78: Arkansas, United States | L78: Maryland | M78: United States | N78: Maryland, United States | O78: Your cells dying faster than they can be replaced | P78: 15 | Q78: 15% or less | R78: Changing opinions | S78: Replacing the workforce, as an aging population's most immediate effects would be in the jobs they leave and the economic downturn. | U78: No, if anything they are actively exacurbating up the issue | V78: Mental flexibility, ability to have fun, an able body | W78: Not currently | X78: Trying to help the next generation | Y78: 2 | Z78: 1 | AA78: 3 | AB78: 2 | AC78: 1 | AD78: 3 | AE78: The third option wouldn't have as much of an impact without the other two already being accomplished, and the second option can indirectly induce the first option | AF78: AI/ML for aging & health | AH78: Reproductive health & longevity | AJ78: Yes | AK78: AI usage, immigration policy, reproductive rights, abortion | AL78: Yes | AO78: Yes
A79: G2-003 | B79: 2 | C79: 11 | F79: 19 | G79: =IF(F79="","",IF(F79>=Notes!$B$5,"Elderly ("&Notes!$B$5&"+)",IF(F79<=Notes!$B$4,"Student age (≤"&Notes!$B$4&")","Middle-aged ("&(Notes!$B$4+1)&"–"&(Notes!$B$5-1)&")"))) -> Student age (≤29) | H79: Female | I79: Ohio | J79: United States | K79: Ohio, United States | L79: Maryland | M79: United States | N79: Maryland, United States | O79: The progressive deterioration of bodily function with time and wear/tear - physically, mentally, and socially. | P79: 20 | Q79: 16–20% | R79: Lack of social and financial infrastructure to support aging individuals - the retirement age keeps rising and I think it puts more stress on the elderly. | S79: Access to healthy food and accessible exercise sources. Key because preventative/lifestyle medicine is the healthiest and most moderate intervention. | U79: No | V79: Autonomy, Agility, Flexibility | W79: Weightlifting, yoga, reading | X79: i. Lengthening the window of fertility for women, and improving overall fertility; ii. Making therapeutics more accessible to people of all socioeconomic backgrounds; iii. Accelerating the development of therapies and risk prediction, making earlier intervention more possible. | Y79: 3 | Z79: 1 | AA79: 2 | AB79: 3 | AC79: 1 | AD79: 2 | AE79: Because I believe that accessibility when developing medical innovation is very important. I also think ML and AI can help make precision care medicine more affordable for patients in the future. | AF79: Democratizing longevity (access) | AH79: AI/ML for aging & health | AJ79: Yes | AK79: Patient anonymity when using ML solutions - especially to prevent insurance rates hiking (illegal). | AL79: Yes | AO79: Yes
A80: G2-004 | B80: 2 | C80: 14 | F80: 21 | G80: =IF(F80="","",IF(F80>=Notes!$B$5,"Elderly ("&Notes!$B$5&"+)",IF(F80<=Notes!$B$4,"Student age (≤"&Notes!$B$4&")","Middle-aged ("&(Notes!$B$4+1)&"–"&(Notes!$B$5-1)&")"))) -> Student age (≤29) | H80: Female | I80: New Jersey | J80: United States | K80: New Jersey, United States | L80: Maryland | M80: United States | N80: Maryland, United States | O80: The natural course of growing old. | P80: 20 | Q80: 16–20% | R80: limited resources and lack of care | S80: As the aging population is increasing rapidly over the years, there is not enough people nor resources to support them through the rapidly changing world, creating a gap between this population and the younger population. This should be prioritized to create a more cohesive society. | U80: Telehealth or AI assistants, community engagement activities | V80: Health, friends, at least one hobby | W80: Exercise and healthy-ish diet, maintaining social connections, finding a hobby that I practice very often | X80: i. How to achieve longer and healthier lives through improving infrastructure and technology around reproductive health and longevity.; ii. Making technologies around longevity available to as many communities as possible, not just people with certain race, socioeconomic status, etc.; iii. Using AI to find patterns in data to help target diseases or provide specific resources for certain populations, or to predict risks in different populations, or to help with drug or therapy development. | Y80: 3 | Z80: 1 | AA80: 2 | AB80: 2 | AC80: 1 | AD80: 3 | AE80: I ranked ii first because no developed technology or solutions can help society without making it affordable and accessible for all. | AF80: AI/ML for aging & health | AH80: Democratizing longevity (access) | AJ80: Yes | AK80: Again as I mentioned, if technology is only available to some groups and not the others, this raises ethical concerns of separating groups based on their eligibility or whether they can afford to live longer. | AL80: Yes | AO80: Yes
A81: G2-005 | B81: 2 | C81: 17 | F81: 21 | G81: =IF(F81="","",IF(F81>=Notes!$B$5,"Elderly ("&Notes!$B$5&"+)",IF(F81<=Notes!$B$4,"Student age (≤"&Notes!$B$4&")","Middle-aged ("&(Notes!$B$4+1)&"–"&(Notes!$B$5-1)&")"))) -> Student age (≤29) | H81: Female | I81: Maryland | J81: United States | K81: Maryland, United States | L81: Maryland | M81: United States | N81: Maryland, United States | O81: Aging is | P81: 30 | Q81: 21–30% | R81: Housing | S81: Nursing homes are becoming more and more expensive, and thus out of reach for many retirees who need the help. Also, due to the general housing prices, home ownership is not easily obtainable for many adults, who end up renting and often do not have the space to take in their parents. | U81: Not really | V81: General mental acuity, hair, good skin | W81: Skincare (sunscreen, lotions, no products with harsh chemical formulations, etc) | X81: i) This involves driving structural support through policy, funding, and institutional frameworks to accelerate research and expand access to care that extends reproductive health and functional lifespan; ii) This involves enhancing monetary and physical access to longevity care and health solutions in a way that takes all stakeholder concerns into account from both a policy and research/development perspective; iii) This involves integrating AI tools into existing workflows in order to utilize available data and improve patient outcomes while maintaining physician input and oversight | Y81: 1 | Z81: 2 | AA81: 3 | AB81: 2 | AC81: 1 | AD81: 3 | AE81: From a societal standpoint, democratizing the process allows for more accessible solutions and thus contributes more to general stability. Simply boosting reproductive health and longevity only benefits those with the existing ability to pay and participate in the healthcare system, and a significant portion of individuals would not benefit. It is important to not overlook the significance of expanding care, especially when it is listed (at least in the US) as one of the top voter concerns for the past 10 years. | AF81: Reproductive health & longevity | AH81: Democratizing longevity (access) | AJ81: Yes | AK81: When developing solutions for longevity, reproductive health, and AI-driven healthcare, significant ethical considerations emerge around stakeholder power dynamics and equitable access. Because financial backing and institutional authority often skew decision-making toward clinicians, policymakers, and corporations while sidelining patients, it is important to guard against these sorts of injustice by making sure all stakeholders have a voice in the process and ensuring that patient-centric realities are not overridden by administrative efficiency. Additionally, combining machine learning with democratization efforts introduces critical challenges regarding healthspan inequality, especially in terms of algorithmic bias, data privacy and data autonomy, which require careful safeguards to ensure fairness and protect individual privacy across diverse and vulnerable populations. | AL81: Yes | AO81: Yes
A82: G2-006 | B82: 2 | C82: 20 | F82: 21 | G82: =IF(F82="","",IF(F82>=Notes!$B$5,"Elderly ("&Notes!$B$5&"+)",IF(F82<=Notes!$B$4,"Student age (≤"&Notes!$B$4&")","Middle-aged ("&(Notes!$B$4+1)&"–"&(Notes!$B$5-1)&")"))) -> Student age (≤29) | H82: Female | I82: New York | J82: United States | K82: New York, United States | L82: Maryland | M82: United States | N82: Maryland, United States | O82: endurance through the progression of time | P82: 20 | Q82: 16–20% | R82: loneliness | S82: better standard of living for ALL and not just those who can afford it. should be a priority because of wealth disparity issues | U82: no | V82: relationships, physical well-being, contentness | W82: investing in my retirement account and taking good care of myself | X82: i) i do not know ii) making developments available to everyone iii) using ai tools to help the aging population directly or using them to make solutions | Y82: 2 | Z82: 1 | AA82: 3 | AB82: 2 | AC82: 1 | AD82: 3 | AE82: because i think we first need to do the most good for the most people, doesn’t matter if that is with or without ai | AF82: Democratizing longevity (access) | AH82: AI/ML for aging & health | AJ82: Yes | AK82: so many ethical and legal concerns with the use of ai, especially as it pertains to our social relationships. risk of extreme dependence, model alignment, unethical training and deployment, etc | AL82: Yes | AO82: Yes
A83: G2-007 | B83: 2 | C83: 21 | F83: 20 | G83: =IF(F83="","",IF(F83>=Notes!$B$5,"Elderly ("&Notes!$B$5&"+)",IF(F83<=Notes!$B$4,"Student age (≤"&Notes!$B$4&")","Middle-aged ("&(Notes!$B$4+1)&"–"&(Notes!$B$5-1)&")"))) -> Student age (≤29) | H83: Female | I83: Oklahoma | J83: United States | K83: Oklahoma, United States | L83: Maryland | M83: United States | N83: Maryland, United States | O83: To me, aging is the biological process of human maturation. | P83: 15 | Q83: 15% or less | R83: Too large of a dependent population, not enough of an adult population to provide for elders. Also social isolation. | S83: Social Isolation is the most preventable and should be prioritized. | U83: In theory there are volunteer programs. | V83: Health, social life, passion. | W83: Keeping 10k steps a day and eating healthy(ish), maintaining social connections. | X83: 1. Checking hormonal levels and following the advice of specialized doctors; 2. Enabling public access by removing financial and geographical barriers; 3. Creating algorithms for efficiency in biomedical applications | Y83: 3 | Z83: 1 | AA83: 2 | AB83: 2 | AC83: 3 | AD83: 1 | AE83: I think people are obsessed with all the ways AI can be applied to healthcare, and I think there’s been a rise in concern for reproductive health/vitality. I don’t think democratizing healthcare solutions will ever be a priority within private healthcare (Despite the good it would do). | AF83: Democratizing longevity (access) | AH83: Democratizing longevity (access) | AJ83: Yes | AK83: Privacy, AI hallucinations and discrimination, financial barriers, etc. | AL83: Yes | AO83: Yes
A84: G2-008 | B84: 2 | C84: 24 | F84: 59 | G84: =IF(F84="","",IF(F84>=Notes!$B$5,"Elderly ("&Notes!$B$5&"+)",IF(F84<=Notes!$B$4,"Student age (≤"&Notes!$B$4&")","Middle-aged ("&(Notes!$B$4+1)&"–"&(Notes!$B$5-1)&")"))) -> Middle-aged (30–64) | H84: Male | J84: Greece | K84: Greece | M84: Greece | N84: Greece | O84: lower endurance, less flexibility, slower responsiveness | P84: 45 | Q84: Over 30% | R84: Better health | S84: Solving the larger fraction of cancers, or at least offering a good life for the patients | U84: Yes, I hear and read that research is advancing in this | V84: Hearing, flexibility, sexual arousal | W84: Leading an active life, exercising, keeping my mind alert | X84: (i) This is about not only living more but living better. (ii) Offering better health to more and more people. (iii) Make technology really work for improving our lives as we age. | Y84: 1 | Z84: 3 | AA84: 2 | AB84: 2 | AC84: 3 | AD84: 1 | AE84: Because public health is the utmost objective for society while well being is my personal aim | AF84: Reproductive health & longevity | AH84: Democratizing longevity (access) | AJ84: Yes | AK84: The obvious ethical questions on AI using our personal health data. | AL84: Yes | AO84: Yes
A85: G2-009 | B85: 2 | C85: 25 | F85: 43 | G85: =IF(F85="","",IF(F85>=Notes!$B$5,"Elderly ("&Notes!$B$5&"+)",IF(F85<=Notes!$B$4,"Student age (≤"&Notes!$B$4&")","Middle-aged ("&(Notes!$B$4+1)&"–"&(Notes!$B$5-1)&")"))) -> Middle-aged (30–64) | H85: Male | J85: Greece | K85: Greece | M85: Greece | N85: Greece | O85: Slower recevery from injuries | P85: 25 | Q85: 21–30% | R85: mobility | S85: mobility | U85: No | V85: brain power, moving ability | W85: weights | X85: global sustainable aging | Y85: 2 | Z85: 1 | AA85: 3 | AB85: 1 | AC85: 2 | AD85: 3 | AE85: Personal view | AF85: Democratizing longevity (access) | AH85: Reproductive health & longevity | AJ85: Yes | AK85: equal access | AL85: Yes | AO85: Yes
A86: G2-010 | B86: 2 | C86: 26 | F86: 60 | G86: =IF(F86="","",IF(F86>=Notes!$B$5,"Elderly ("&Notes!$B$5&"+)",IF(F86<=Notes!$B$4,"Student age (≤"&Notes!$B$4&")","Middle-aged ("&(Notes!$B$4+1)&"–"&(Notes!$B$5-1)&")"))) -> Middle-aged (30–64) | H86: Male | J86: Greece | K86: Greece | L86: Attica | M86: Greece | N86: Attica, Greece | O86: Searching for the energy to do things as opposed to have energy in abundance while young.. | P86: 25 | Q86: 21–30% | R86: To manage to maintain their quality of life.. | S86: The sense of community and friendship which can erode on various fronts surprisingly fast as we get older in the ‘old’ sense of the term… | U86: On the contrary, people get increasingly isolated… | V86: Health, kinship and participation | W86: Trying to maintain all three.. | X86: i: Living longer without giving up intimacy; ii: Our solutions to be accessible to all; iii: Adopting the newest technologies towards the noted goals… | Y86: 1 | Z86: 2 | AA86: 3 | AB86: 3 | AC86: 1 | AD86: 2 | AE86: My ‘feel’ for them.. | AF86: Democratizing longevity (access) | AH86: Democratizing longevity (access) | AJ86: Yes | AK86: Those who are ‘left behind’.. | AL86: Yes | AO86: Yes
A87: G2-011 | B87: 2 | C87: 29 | F87: 70 | G87: =IF(F87="","",IF(F87>=Notes!$B$5,"Elderly ("&Notes!$B$5&"+)",IF(F87<=Notes!$B$4,"Student age (≤"&Notes!$B$4&")","Middle-aged ("&(Notes!$B$4+1)&"–"&(Notes!$B$5-1)&")"))) -> Elderly (65+) | H87: Male | J87: Greece | K87: Greece | M87: Greece | N87: Greece | O87: It is wonderful aging. You are getting more wise. | P87: 60 | Q87: Over 30% | R87: Keep them happy and healthy | S87: Avoiding loneliness | U87: It works in smaller communities also through family unity | V87: Physical health clear mind and communication | W87: Working although in retirement | X87: Machine learning and AI to be under control Leaving in an open community. | Y87: 1 | Z87: 2 | AA87: 3 | AB87: 1 | AC87: 2 | AD87: 3 | AE87: Because it's more sentimental approach | AF87: Reproductive health & longevity | AH87: AI/ML for aging & health | AJ87: Yes | AK87: mankind thinking over machine | AN87: I don't think there is much left to discover. | AO87: Yes
A88: G2-012 | B88: 2 | C88: 30 | F88: 20 | G88: =IF(F88="","",IF(F88>=Notes!$B$5,"Elderly ("&Notes!$B$5&"+)",IF(F88<=Notes!$B$4,"Student age (≤"&Notes!$B$4&")","Middle-aged ("&(Notes!$B$4+1)&"–"&(Notes!$B$5-1)&")"))) -> Student age (≤29) | H88: Female | I88: California | J88: United States | K88: California, United States | L88: Maryland | M88: United States | N88: Maryland, United States | O88: Aging is the process of becoming an older member of society, which also includes retirement from the job market and, increased health risks. | P88: 35 | Q88: Over 30% | R88: Loneliness, finding purpose in life, limited social security benefits | S88: Loneliness and limited social security must be addressed for the aging population as these are key determinants of health outcomes. | U88: Not much action | V88: Empathy, humor, compassion | W88: Continually doing community service and sharing the importance of it with younger generations | X88: I. Having increased education for people who can reproduce and how to take care of their bodies after giving birth while also promoting healthy longevity practices for the entire population; II. Making longevity and health solutions public knowledge and allowing it to be accessible by all; Iii. Utilizing AI and machine learning to come up wigr modern solutions and analyze present-day patterns in the aging population | Y88: 2 | Z88: 1 | AA88: 3 | AB88: 2 | AC88: 3 | AD88: 1 | AE88: Longevity and health solutions must be made available to everyone first before we can apply machine learning and AI in my opinion, however, society would likely tend to let AI solve the issues faster without regard to those who may not be able to benefit from AI/ tech based solutions. | AF88: Democratizing longevity (access) | AH88: Democratizing longevity (access) | AJ88: Yes | AK88: How to test if these interventions are actually viable in a group of aging individuals | AL88: Yes | AO88: Yes
A89: G2-013 | B89: 2 | C89: 33 | F89: 20 | G89: =IF(F89="","",IF(F89>=Notes!$B$5,"Elderly ("&Notes!$B$5&"+)",IF(F89<=Notes!$B$4,"Student age (≤"&Notes!$B$4&")","Middle-aged ("&(Notes!$B$4+1)&"–"&(Notes!$B$5-1)&")"))) -> Student age (≤29) | H89: Female | I89: Pennsylvania | J89: United States | K89: Pennsylvania, United States | L89: Maryland | M89: United States | N89: Maryland, United States | O89: As you get older, your body and mind changes. | P89: 25 | Q89: 21–30% | R89: Unaccessible healthcare system | S89: I think in short term it’s important to build community both within the elderly population but also connecting them to younger people. | U89: No | V89: Mental capability, ability to move independently, and my senses | W89: Continue learning, take care of my body, trying not to remain stagnant, maintain healthy relationships | X89: Improving reproductive health through research and funding and awareness. Improving accessibility to health solutions that can help the aging population to ensure equal ability to utilize the resources. Use AI to improve robustness for research on health solutions for the elderly | Y89: 1 | Z89: 2 | AA89: 3 | AB89: 1 | AC89: 2 | AD89: 3 | AE89: Specifically female reproductive health is incredibly important and underdeveloped. Next I think it’s incredible important for medical solutions to be equally accessible. I don’t care if AI is used for health solutions as long as they’re being made accurately with human oversight. | AF89: Reproductive health & longevity | AH89: AI/ML for aging & health | AJ89: Yes | AK89: When making medical development it should be certain they will not be used unequally to only improve certain people’s lives in society who have more money or some other privilege, and it’s important it is certain the development is thoroughly tested for everyone. | AL89: Yes | AO89: Yes
A90: G2-014 | B90: 2 | C90: 34 | F90: 22 | G90: =IF(F90="","",IF(F90>=Notes!$B$5,"Elderly ("&Notes!$B$5&"+)",IF(F90<=Notes!$B$4,"Student age (≤"&Notes!$B$4&")","Middle-aged ("&(Notes!$B$4+1)&"–"&(Notes!$B$5-1)&")"))) -> Student age (≤29) | H90: Female | I90: Virginia | J90: United States | K90: Virginia, United States | L90: Maryland | M90: United States | N90: Maryland, United States | O90: I would define aging as a biological process of growing older. Typically, we see physical changes such as wrinkles and grey hair as well as biological changes such as being prone to more diseases. | P90: 70 | Q90: Over 30% | R90: That they are more prone to get diseases compared to the younger populations (14-35). | S90: I would say if there was a way to stabilize or reduce aging, then that would be a potential solution. It should be prioritized because you are getting to the root of the issue rather than tackling other challenges that may just be temporary. | U90: I think research may be going on, but not sure. | V90: Being physical (active), good mental health, being social | W90: Trying to make sure that I do these things while I am young, so that as I age, I should maintain the same habits | X90: i) Making sure everyone is aware of reproductive health and how it can be maintained; ii) Solving issues using research and technology and making sure that everyone can access and afford it; iii) Using AI to help with tracking changes as humans age as well as potentially coming up with solutions for aging | Y90: 2 | Z90: 1 | AA90: 3 | AB90: 3 | AC90: 1 | AD90: 2 | AE90: I think (ii) is very important because I think that everyone should be able to afford the new solutions that we come up with to help with aging. (iii) is important, but not as important as the other two because I feel like AI is just starting to grow, and I feel as though we should be able to solve problems and track the problems as we used to before AI. | AF90: Democratizing longevity (access) | AH90: AI/ML for aging & health | AJ90: Yes | AK90: One ethical consideration is should we consider aging as a disease, or just a natural part of life that we just need to accept? | AL90: Yes | AO90: Yes
A91: G2-015 | B91: 2 | C91: 37 | F91: 14 | G91: =IF(F91="","",IF(F91>=Notes!$B$5,"Elderly ("&Notes!$B$5&"+)",IF(F91<=Notes!$B$4,"Student age (≤"&Notes!$B$4&")","Middle-aged ("&(Notes!$B$4+1)&"–"&(Notes!$B$5-1)&")"))) -> Student age (≤29) | H91: Male | I91: Virginia | J91: United States | K91: Virginia, United States | L91: Virginia | M91: United States | N91: Virginia, United States | O91: Someone’s body and mind slowly growing to a peak point then degrading. | P91: 40 | Q91: Over 30% | R91: Healthcare and convenience of things. | S91: The healthcare should be solved, because a lot of the treatments can prioritize middle-aged people and younger, while the elderly don’t get all the same treatment. | U91: Not at the moment, but I do not follow healthcare news at all. | V91: Memories, skills I’ve learned (like playing guitar) and musical knowledge | W91: Keeping practicing and keeping my mind and body fit | X91: I. Bringing up the age where it is healthy to reproduce without health problems.; II. Making healthcare affordable and attainable for everyone; III. Using AI and machine learning to help with speeding up medical discoveries | Y91: 2 | Z91: 1 | AA91: 3 | AB91: 3 | AC91: 1 | AD91: 2 | AE91: People would focus most on AI stuff and getting healthcare than reproductive things in my opinion. | AF91: Democratizing longevity (access) | AH91: AI/ML for aging & health | AJ91: Yes | AK91: They are humans, so we need to keep that in mind due to everyone being different. | AL91: No | AO91: Yes
A92: G2-016 | B92: 2 | C92: 40 | F92: 14 | G92: =IF(F92="","",IF(F92>=Notes!$B$5,"Elderly ("&Notes!$B$5&"+)",IF(F92<=Notes!$B$4,"Student age (≤"&Notes!$B$4&")","Middle-aged ("&(Notes!$B$4+1)&"–"&(Notes!$B$5-1)&")"))) -> Student age (≤29) | H92: Female | I92: Virginia | J92: United States | K92: Virginia, United States | L92: Virginia | M92: United States | N92: Virginia, United States | O92: aging is the act of becoming older. we all are aging by the very second - theres no escaping our evident fate. | P92: 25 | Q92: 21–30% | R92: They don't have the needs to find resources to help them medically. | S92: One challenge is the money for getting medical resources to help them to continue living. It should be prioritized because these are people who love and care about us, and we should care to allow them to continue living for generations more. | U92: Not that I know of | V92: Health, wealth, and kindness | W92: Not at the moment, but I plan to. | X92: i) Lengthening the time you can have children/reproduce; ii) Have medical resources to live longer be more affordable; iii) Having AI collaborate with medicine to make better machines | Y92: 3 | Z92: 1 | AA92: 2 | AB92: 2 | AC92: 3 | AD92: 1 | AE92: Society's needs versus my needs are different. | AF92: Democratizing longevity (access) | AH92: AI/ML for aging & health | AJ92: Yes | AK92: Don't hurt animals, and don't waste the water resources - be sustainable, etc. | AL92: Yes | AO92: Yes
A93: G2-017 | B93: 2 | C93: 43 | F93: 22 | G93: =IF(F93="","",IF(F93>=Notes!$B$5,"Elderly ("&Notes!$B$5&"+)",IF(F93<=Notes!$B$4,"Student age (≤"&Notes!$B$4&")","Middle-aged ("&(Notes!$B$4+1)&"–"&(Notes!$B$5-1)&")"))) -> Student age (≤29) | H93: Female | I93: Virginia | J93: United States | K93: Virginia, United States | L93: Virginia | M93: United States | N93: Virginia, United States | O93: Aging just means getting older and changing over time. | P93: 15 | Q93: 15% or less | R93: Healthcare access. Independent living. Socioeconomic status. | S93: Ensuring financial and economic security. | U93: No, not at all. | V93: Physical mobility. Social interaction. | W93: Yes, I make sure to take care of my health my maintaining a proper diet and exercise regularly. Additionally, I make sure to stay in touch and maintain my relationships with people I’m close with. | X93: Boosting reproductive health and longevity focuses on improving reproductive health while promoting longer and healthier lives, democratizing longevity science and solutions focuses on making longevity and health solutions more accessible, affordable, and applicable to a wider population, and applying machine learning and AI to aging and health focuses on using AI and machine learning to better understand and predict health outcomes, such as disease risk and progression. | Y93: 1 | Z93: 2 | AA93: 3 | AB93: 3 | AC93: 2 | AD93: 1 | AE93: Based on political and societal beliefs that are present today. | AF93: Reproductive health & longevity | AH93: AI/ML for aging & health | AJ93: Yes | AK93: I think there are ethical considerations we should keep in mind, including protecting patient privacy, making sure the data used to train AI are accurate and representative, and avoiding bias that could lead to differences in health outcomes. | AL93: Yes | AO93: Yes
A94: G2-018 | B94: 2 | C94: 44 | F94: 21 | G94: =IF(F94="","",IF(F94>=Notes!$B$5,"Elderly ("&Notes!$B$5&"+)",IF(F94<=Notes!$B$4,"Student age (≤"&Notes!$B$4&")","Middle-aged ("&(Notes!$B$4+1)&"–"&(Notes!$B$5-1)&")"))) -> Student age (≤29) | H94: Female | I94: Wisconsin | J94: United States | K94: Wisconsin, United States | L94: Maryland | M94: United States | N94: Maryland, United States | O94: The process of getting progressively older both mentally and physically. | P94: 20 | Q94: 16–20% | R94: Support, Access to care. | S94: Having better in home health care. | U94: I think people are talking more about aging populations but there is a lot of talk and not a lot of action. | V94: Independence, memory, energy | W94: I am trying to be as healthy as I can be both physically and mentally. | X94: i Increasing access and knowledge of reproductive health and by addressing factors that influence fertility, pregnancy outcomes, reproductive aging, and long-term health. ii making care more accessible and easy to get for all populations. iii using AI to develop more productive forms of care and ease. | Y94: 2 | Z94: 1 | AA94: 3 | AB94: 2 | AC94: 1 | AD94: 3 | AE94: I think first and foremost access to care is important. Nobody should be struggling to be heard and seen. I think reproductive health is something that women that a lot of people struggle with so its an important concept to consider and promote. AI although it can have a lot of benefits has a lot of potential ethical concerns and things that could go wrong and be detrimental to society. | AF94: Reproductive health & longevity | AH94: AI/ML for aging & health | AJ94: Yes | AK94: Who has access to this, who the AI is trained out, what are the checks to make sure it is giving correct information. | AL94: Yes | AO94: Yes
A95: G2-019 | B95: 2 | C95: 45 | F95: 48 | G95: =IF(F95="","",IF(F95>=Notes!$B$5,"Elderly ("&Notes!$B$5&"+)",IF(F95<=Notes!$B$4,"Student age (≤"&Notes!$B$4&")","Middle-aged ("&(Notes!$B$4+1)&"–"&(Notes!$B$5-1)&")"))) -> Middle-aged (30–64) | H95: Female | J95: India | K95: India | L95: Virginia | M95: United States | N95: Virginia, United States | O95: Aging is growing wisdom, graying of hair and accumulating lots of friends and memories | P95: 60 | Q95: Over 30% | R95: Loneliness, lack of caregivers at home and lots of medical bills | S95: Lack of home-based trusted caregivers; having someone taking care at home who can be fully trusted helps the aging person feel secure and can improve mental well-being | U95: Home health aide agencies are slowly growing in numbers | V95: Physical fitness, mental well-being and social support (friends) | W95: Regular exercise, meditation and social engagement | X95: (i) - identification of various ways to improve fertility; (ii) - having accessible and affordable healthcare and fitness options to all income groups; (iii) - identification of health anomalies using fitness tracking devices and wellness check-ups data can help with building proactive measures to prevent big health incidents | Y95: 3 | Z95: 1 | AA95: 2 | AB95: 2 | AC95: 1 | AD95: 3 | AE95: I value longevity & health solutions as well as understand the value of data-backed solutions | AF95: AI/ML for aging & health | AH95: Democratizing longevity (access) | AJ95: Yes | AK95: Human consent in solutions should be of highest value; privacy intrusion should be avoided | AL95: Yes | AO95: Yes
A96: G2-020 | B96: 2 | C96: 48 | F96: 22 | G96: =IF(F96="","",IF(F96>=Notes!$B$5,"Elderly ("&Notes!$B$5&"+)",IF(F96<=Notes!$B$4,"Student age (≤"&Notes!$B$4&")","Middle-aged ("&(Notes!$B$4+1)&"–"&(Notes!$B$5-1)&")"))) -> Student age (≤29) | H96: Female | I96: California | J96: United States | K96: California, United States | L96: Georgia | M96: United States | N96: Georgia, United States | O96: I think aging is defined as growing up mentally and taking on more responsibilities without the help of an adult. | P96: 40 | Q96: Over 30% | R96: Interacting with the younger population. | S96: Extending life expectancy | U96: Yes, I feel like many innovations are out there at making quality of life and extending life. | V96: Quality of life, ability to drive, ability to communicate | W96: Exercise and eating well | X96: Bioengineering | Y96: 1 | Z96: 2 | AA96: 3 | AB96: 2 | AC96: 3 | AD96: 1 | AE96: AI is becoming more prevalent and important | AF96: Reproductive health & longevity | AH96: Reproductive health & longevity | AJ96: Yes | AK96: How much should AI know and learn from | AL96: Yes | AO96: Yes
A97: G2-021 | B97: 2 | C97: 49 | F97: 21 | G97: =IF(F97="","",IF(F97>=Notes!$B$5,"Elderly ("&Notes!$B$5&"+)",IF(F97<=Notes!$B$4,"Student age (≤"&Notes!$B$4&")","Middle-aged ("&(Notes!$B$4+1)&"–"&(Notes!$B$5-1)&")"))) -> Student age (≤29) | H97: Male | I97: Oregon | J97: United States | K97: Oregon, United States | L97: Maryland | M97: United States | N97: Maryland, United States | O97: Experiencing the passing of time. | P97: 25 | Q97: 21–30% | R97: General health | S97: I think diet should be solved in the near future. It should be a priority because of how fundamental it is, and low cost. | U97: Yes. | V97: Mobility, Energy, Cognition | W97: Regular exercise, moderate diet. | X97: i) Increasing the window that people can have healthy kids in.; ii) Lowering the barrier to knowledge and healthcare resources.; iii) Using large datasets to understand our own health trajectories, and customize solutions. | Y97: 1 | Z97: 2 | AA97: 3 | AB97: 1 | AC97: 3 | AD97: 2 | AE97: I am concerned about population aging/decline. And I think access is generally a consequence of other inequalities, so see it as an inefficient focus. | AF97: AI/ML for aging & health | AH97: Reproductive health & longevity | AJ97: Yes | AK97: Embryonic research, gene modification | AL97: Yes | AO97: Yes
A98: G2-022 | B98: 2 | C98: 52 | F98: 21 | G98: =IF(F98="","",IF(F98>=Notes!$B$5,"Elderly ("&Notes!$B$5&"+)",IF(F98<=Notes!$B$4,"Student age (≤"&Notes!$B$4&")","Middle-aged ("&(Notes!$B$4+1)&"–"&(Notes!$B$5-1)&")"))) -> Student age (≤29) | H98: Female | I98: New York | J98: United States | K98: New York, United States | L98: Maryland | M98: United States | N98: Maryland, United States | O98: The process of getting older | P98: 30 | Q98: 21–30% | R98: Lack of support | S98: Health care for all needs to be prioritized because everyone deserves health. | U98: Not in current political climate unfortunately | V98: Health, happiness, independence | W98: Exercise, nutrition, sleep, limit alcohol intake, go to the doctor, rest | X98: (I) protecting access to reproductive health care and improving education surrounding reproductive health; (II) health care access to all, including preventative; (III) using artificial intelligence to make predictions and solutions for health and longevity | Y98: 1 | Z98: 2 | AA98: 3 | AB98: 1 | AC98: 2 | AD98: 3 | AE98: I think reproductive health care is incredibly important in the present moment as well as the future and it is currently under threat. I similarly believe equal health care access is incredibly important. I am more skeptical of AI usage due to possible data breaches and lack of addressing systemic issues. | AF98: Reproductive health & longevity | AH98: AI/ML for aging & health | AJ98: Yes | AK98: AI usage, privacy, data, emphasis on choice | AL98: Yes | AO98: Yes
A99: G2-023 | B99: 2 | C99: 55 | F99: 21 | G99: =IF(F99="","",IF(F99>=Notes!$B$5,"Elderly ("&Notes!$B$5&"+)",IF(F99<=Notes!$B$4,"Student age (≤"&Notes!$B$4&")","Middle-aged ("&(Notes!$B$4+1)&"–"&(Notes!$B$5-1)&")"))) -> Student age (≤29) | H99: Female | I99: New Jersey | J99: United States | K99: New Jersey, United States | L99: Maryland | M99: United States | N99: Maryland, United States | O99: Getting older and growing. | P99: 20 | Q99: 16–20% | R99: chemicals in food and air | S99: same as above | U99: no | V99: my athletic health, good joints, strong muscles | W99: yes, eat healthy and exercise | X99: Making more babies, making healthier people, using AI | Y99: 2 | Z99: 1 | AA99: 3 | AB99: 1 | AC99: 3 | AD99: 2 | AE99: seemed appropriate | AF99: Democratizing longevity (access) | AH99: AI/ML for aging & health | AJ99: Yes | AK99: the AI part, and genetically modifying a baby | AL99: Yes | AO99: Yes
A100: G2-024 | B100: 2 | C100: 56 | F100: 54 | G100: =IF(F100="","",IF(F100>=Notes!$B$5,"Elderly ("&Notes!$B$5&"+)",IF(F100<=Notes!$B$4,"Student age (≤"&Notes!$B$4&")","Middle-aged ("&(Notes!$B$4+1)&"–"&(Notes!$B$5-1)&")"))) -> Middle-aged (30–64) | H100: Female | I100: Oregon | J100: United States | K100: Oregon, United States | L100: Oregon | M100: United States | N100: Oregon, United States | O100: Aging is when you physically begin to undergo changes over time. | P100: 25 | Q100: 21–30% | R100: Healthcare loneliness depression | S100: Loneliness is an issue that would help our aging population. We need community based activities to help them socially, emotionally and mentally. | U100: Not that I know of beyond private elder care centers which are very costly and prohibitive. | V100: Mental and physical health community, | W100: Exercising spending time with family and friends book club | X100: Increasing longevity by supporting reproductive health. Healthcare access without barriers to increase longevity. Using AI to increase longevity. | Y100: 1 | Z100: 2 | AA100: 3 | AB100: 2 | AC100: 1 | AD100: 3 | AE100: I am somewhat skeptical of AI taking over too much. | AF100: Reproductive health & longevity | AH100: AI/ML for aging & health | AJ100: Yes | AK100: I think we have to always consider the moral and ethical ramifications of all decisions. We need to put ethics above profit. | AL100: Yes | AO100: Yes
...

Sheet Tagged Responses
A1: Respondent ID | B1: Group | C1: Age | D1: Age category | E1: Gender | F1: From – Country | G1: Residence – Country | H1: Q5 Definition of aging – response | I1: Q5 Definition of aging – themes | J1: Q7 Greatest challenge – response | K1: Q7 Greatest challenge – themes | L1: Q8 Short-term priority – response | M1: Q8 Short-term priority – themes | N1: Q9 Is action being taken? – response | O1: Q9 Is action being taken? – status | P1: Q10 Things to maintain – response | Q1: Q10 Things to maintain – themes | R1: Q11 What you can do – response | S1: Q11 What you can do – themes | T1: Reason for topic ranking – response | U1: Reason for topic ranking – themes | V1: What excites you – response | W1: What excites you – themes | X1: Greatest concern – response | Y1: Greatest concern – themes | Z1: Ethical considerations – response | AA1: Ethical considerations – themes
A2: G1-001 | B2: 1 | C2: 25 | D2: =Combined!G2 -> Student age (≤29) | E2: Female | F2: United States | G2: United States | H2: Biological and physical changes as a result of time passing! | I2: Biological / cellular process; Passage of time / getting older; Physical & bodily change | J2: Not enough access to medical care/practitioners. | K2: Access, cost & equity; Healthcare system & caregiving | L2: Promote programs to get more caregivers/nursing home attendants | M2: Healthcare system & caregiving | N2: Programs to sponsor people who plan to be or are caregivers (forgiven college debts), subsidies, free food delivery programs for elderly | O2: Names an action or idea | P2: My mind, my friends, my ability to move easily | Q2: Physical health & mobility; Memory & cognitive sharpness; Relationships & social life | R2: Yoga, reading, going to yoga with friends lol | S2: Exercise & physical activity; Social engagement; Learning & mental stimulation | V2: As a woman, it is scary to feel pressured to have children when there is little access to good childcare for working women. | W2: Access, cost & equity; Reproductive health & fertility
A3: G1-002 | B3: 1 | C3: 24 | D3: =Combined!G3 -> Student age (≤29) | E3: Female | F3: United States | G3: United States | H3: body tissues breaking down, mind gaining experience | I3: Decline & change in function; Biological / cellular process; Physical & bodily change; Cognitive & mental change; Growth, experience & wisdom | J3: social support | K3: Social connection & isolation | L3: healthcare resource availability | M3: Healthcare system & caregiving | N3: ehh not really | O3: Little or none | P3: mental clarity, mental health, mobility | Q3: Physical health & mobility; Memory & cognitive sharpness; Mental & emotional well-being | R3: eat good sleep good exercise good protect my relationships | S3: Exercise & physical activity; Diet & nutrition; Sleep & rest; Social engagement | V3: dementia | W3: Cognitive decline & dementia
A4: G1-003 | B4: 1 | C4: 19 | D4: =Combined!G4 -> Student age (≤29) | E4: Female | F4: United States | G4: United States | H4: Scary | I4: Mindset / "just a number" | J4: Lack of preventative medicine so diseases and illnesses get caught too late. | K4: Chronic disease & physical health; Research, science & treatments; Prevention & early detection | L4: Preventative medicine can help prevent consequences that later on can be more costly and painful, if we can figure out a way to encourage more people and to get people more access to said preventative medicine in the short term it will solve a lot of our long term problems. | M4: Access, cost & equity; Chronic disease & physical health; Research, science & treatments; Prevention & early detection | N4: No, our administration cuts budgets and doesn’t make healthcare more accessible. | O4: Little or none | P4: Family, physical & mental health | Q4: Physical health & mobility; Mental & emotional well-being; Relationships & social life | R4: I can keep showing up for people to maintain my community, I can also keep going to check ups and I can pay attention to nutrition and exercise in order to keep my health up. | S4: Healthy lifestyle & habits (general); Exercise & physical activity; Diet & nutrition; Social engagement; Preventive & medical care | V4: I mean the concept of AI taking over our healthcare system is scary but it’s also exciting because it may be a lot more accessible to more people. | W4: Access, cost & equity; Healthcare system & caregiving; Technology & AI
A5: G1-004 | B5: 1 | C5: 21 | D5: =Combined!G5 -> Student age (≤29) | E5: Male | F5: United States | G5: United States | H5: telomere degradation | I5: Biological / cellular process | J5: Rising technological advances resulting in increased ignorance | K5: Technology & AI; Research, science & treatments | L5: Lack of help - basic needs -> foundations of a healthy life | M5: Chronic disease & physical health; Financial security, work & basic needs | N5: Reformation of nursing homes and communities currently, but unfortunately insufficient | O5: Some, but insufficient | P5: youthful personality, athleticism, and drive | Q5: Physical health & mobility; Mental & emotional well-being; Hobbies, curiosity & purpose; Values & identity | R5: education | S5: Learning & mental stimulation | V5: AI predicting modern solutions - both excites me for the future of medicine, but also frightens me for the upcoming consequences | W5: Technology & AI; Research, science & treatments; Prevention & early detection
A6: G1-005 | B6: 1 | C6: 21 | D6: =Combined!G6 -> Student age (≤29) | E6: Male | F6: United States | G6: United States | H6: Cellular aging | I6: Biological / cellular process | J6: Aging with dignity | K6: Ageism & how society treats older adults | L6: Demograohic cliff cannot financially support elder cohort | M6: Healthcare system & caregiving; Financial security, work & basic needs | N6: No | O6: Little or none | P6: Money, movement, mental acuity | Q6: Physical health & mobility; Memory & cognitive sharpness; Financial security | R6: Healthy lifestyle | S6: Healthy lifestyle & habits (general) | T6: Idk | U6: No answer / unsure | V6: Idk | W6: No answer / unsure
A7: G1-006 | B7: 1 | C7: 24 | D7: =Combined!G7 -> Student age (≤29) | E7: Male | F7: United States | G7: United States | H7: Getting older | I7: Passage of time / getting older | J7: Dealing with all sorts of age-related diseases/complications | K7: Chronic disease & physical health | L7: Preventative health so we are proactive instead of reactive | M7: Chronic disease & physical health; Prevention & early detection | N7: R&D | O7: Names an action or idea | P7: Vision; Lucidity; Athleticism | Q7: Physical health & mobility; Memory & cognitive sharpness | R7: Workout; Dont use too many screens; Puzzles | S7: Exercise & physical activity; Learning & mental stimulation; Preventive & medical care | T7: I want to be healthy | U7: Personal relevance; Chronic disease & physical health | V7: Longer healthier lives; AI taking over the world | W7: Technology & AI
A8: G1-007 | B8: 1 | C8: 20 | D8: =Combined!G8 -> Student age (≤29) | E8: Male | F8: United States | G8: United States | H8: Chronologically getting older, or biologically degrading telomeres | I8: Biological / cellular process; Passage of time / getting older | J8: More and more aging population, but less and less resources to care for them (both monetarily but also human-labor wise) | K8: Healthcare system & caregiving; Population & societal burden | L8: Find people that are able to give that care at an affordable pace, because without the promise of a worthwhile retirement (age) then people grow less motivated and more focused on trying to make their prime the best it can be. | M8: Access, cost & equity; Financial security, work & basic needs | N8: Make day to day life easier by offering ways for families to take care of their elderly members (leave from work, stipend, etc.) | O8: Names an action or idea | P8: Physical mobility, cognition (mentally active, lose consciouness and become a shell), keep up with the times (not getting stuck in a mindset) | Q8: Physical health & mobility; Memory & cognitive sharpness | R8: Keep an open mind, stay healthy be exercising, don’t get complacent about doing things. | S8: Healthy lifestyle & habits (general); Exercise & physical activity | T8: If you can apply broader health impacts across all walks of life, they would most impact people at the current timeframe, but also probably as they grow older they maintain healthier habits and benefits so it’s more lifelong than specific moments. | U8: Broad benefit to society; Chronic disease & physical health | V8: Not really exciting, but more of a necessity of things that have to happen if we want our lives to get better. There isn’t enough of a rush or consideration for it in the grand scheme of things currently going on, so much division that there isn’t time to focus on these issues | W8: Other
A9: G1-008 | B9: 1 | C9: 20 | D9: =Combined!G9 -> Student age (≤29) | E9: Male | F9: United States | G9: United States | H9: Growing older | I9: Passage of time / getting older | J9: Loneliness | K9: Social connection & isolation | L9: General healthiness | M9: Chronic disease & physical health | N9: Yes, more mental wellbeing being understood and addressed, people starting to be more active on social media | O9: Yes | P9: Health, mental acuity, friends | Q9: Physical health & mobility; Memory & cognitive sharpness; Relationships & social life | R9: Maintain good habits, read books, good communication | S9: Healthy lifestyle & habits (general); Learning & mental stimulation | T9: Accessibility to these longevity/health solutions isn’t as important to me as it is for society since I already have access and have a lesser need for them since I am young. I would be more interested in accelerating research in longevity/health. To society, however, accessibility is the most important as everyone deserves a baseline level of access to currently existing science/solutions. | U9: Personal relevance; Broad benefit to society; Access, cost & equity; Chronic disease & physical health; Research, science & treatments; Longevity & lifespan | V9: Iii, it’s newer, and things that leverage ai just excite me personally. We also have a ton of data compiled from years of research. Something that comes to mind is the PDB. The concern though is that it’s newer so there are potential unknown risks of unknown magnitude. | W9: Technology & AI; Safety, accuracy & misuse; Research, science & treatments
A10: G1-009 | B10: 1 | C10: 21 | D10: =Combined!G10 -> Student age (≤29) | E10: Male | F10: United States | G10: United States | H10: The process of integrating learned/life experiences throughout one's lifetime. | I10: Growth, experience & wisdom | J10: Access to healthcare and socialization | K10: Access, cost & equity; Healthcare system & caregiving; Social connection & isolation | L10: Socialization as issues with healthcare are particularly geared toward a specific group of people while most if not all elderly find it difficult to socialize. | M10: Healthcare system & caregiving; Social connection & isolation | N10: Yes through different social groups or spaces, such as church or even small groups/ clubs. | O10: Yes | P10: My memory, cognitive ability, and physical ability. | Q10: Physical health & mobility; Memory & cognitive sharpness | R10: Maintain my mental and physical routine throughout my lifetime, even as i get older. | S10: Healthy lifestyle & habits (general) | T10: I prioritize making health more accessible to others, while I feel as if general society wants to capitalize on the advancements in AI to find an optimal approach to aging. | U10: Broad benefit to society; Access, cost & equity; Chronic disease & physical health; Technology & AI; Research, science & treatments | V10: ii is most exciting while iii is most concerning. | W10: Other
A11: G1-010 | B11: 1 | C11: 20 | D11: =Combined!G11 -> Student age (≤29) | E11: Male | F11: United States | G11: United States | H11: Being alive for longer | I11: Passage of time / getting older | J11: Medical care/retirement funds | K11: Healthcare system & caregiving; Financial security, work & basic needs | L11: Not enough tax money to pay the retirement funds of the aging population. | M11: Financial security, work & basic needs; Population & societal burden | N11: Increase retirement age or remove social security. | O11: Names an action or idea | P11: Money; Health; Family | Q11: Physical health & mobility; Relationships & social life; Financial security | R11: Make sure I make enough money to keep my health and family. | S11: Social engagement; Financial planning | T11: Health is most important for life. Money is required for health. | U11: Chronic disease & physical health; Financial security, work & basic needs | V11: Excited for boosting reproductive health and longevity lets me live longer and feel better as I live longer. I’m afraid that capitalism will commercialize health even more and make it inaccessible to lower middle income individuals. | W11: Access, cost & equity; Chronic disease & physical health; Financial security, work & basic needs; Longevity & lifespan; Reproductive health & fertility
A12: G1-011 | B12: 1 | C12: 22 | D12: =Combined!G12 -> Student age (≤29) | E12: Female | F12: United States | G12: United States | H12: I think aging is defined as the physical and metabolic/molecular changes that occur within an individual. I believe that there are genetic and environmental factors that can help or hinder a person’s aging rate. I also think that aging is unique to each person because of these factors. | I12: Biological / cellular process; Physical & bodily change | J12: maybe disengagement theory- being ostracized from the population which can lead to feeling alienated from dominant society. | K12: Population & societal burden | L12: I think that the greatest challenge facing our aging population could possibly be them feeling ostracized from the general public, which can affect their mental health and thus cause other health problems. | M12: Chronic disease & physical health; Mental & emotional health; Population & societal burden | N12: Not really. I feel like it’s normal for people to do things with their own age group so that might be a reason why I personally don’t see aging populations doing activities that I like to do. | O12: Little or none | P12: Doing wellness activities (ex. running), reading a lot, being happy. | Q12: Mental & emotional well-being; Hobbies, curiosity & purpose | R12: join groups that are involved in running and living a healthy lifestyle. And hanging out with people who had the same mindset and ideals as me. | S12: Healthy lifestyle & habits (general); Exercise & physical activity; Social engagement | T12: I think people will look at things, face value and care about if the solutions are affordable and accessible to them. | U12: Access, cost & equity | V12: I hope that one day, solutions to aging become accessible to the general public and aren’t expensive and only available to the rich. | W12: Access, cost & equity
A13: G1-012 | B13: 1 | C13: 22 | D13: =Combined!G13 -> Student age (≤29) | E13: Male | F13: United States | G13: United States | H13: The passage of time | I13: Passage of time / getting older | J13: Social security is inadequate for our increasingly aged country | K13: Financial security, work & basic needs | L13: Aged population growth is accelerating while birth rate is declining, having the young take care of the old financially through social security is infeasible, and changes need to be addressed now before the population collapses similar to Korea. | M13: Financial security, work & basic needs; Reproductive health & fertility; Population & societal burden | N13: Increase the retirement age. | O13: Names an action or idea | P13: My physical, mental, and financial health. | Q13: Physical health & mobility; Financial security | R13: Workout and invest heavily | S13: Exercise & physical activity; Financial planning | T13: I think AI will significantly accelerate aging research which will be helpful for everyone. | U13: Broad benefit to society; Access, cost & equity; Technology & AI; Research, science & treatments | V13: Rich people will live longer and control more. | W13: Access, cost & equity; Longevity & lifespan
A14: G1-013 | B14: 1 | C14: 22 | D14: =Combined!G14 -> Student age (≤29) | E14: Male | F14: United States | G14: United States | H14: Being alive longer? | I14: Passage of time / getting older | J14: Healthcare Costs | K14: Access, cost & equity; Healthcare system & caregiving | L14: Healthcare, everyone gets old and more prone to hospital visits. | M14: Access, cost & equity; Healthcare system & caregiving | N14: Honestly no. I know this is unpopular in the largely democratic hopkins space and I am up in the air about how much I truly believe in this idea, I am also kinda ignorant in this topic specifically because I don’t really think or care about the older population very much at this point in my life.; But privatizing advanced medicine isn’t the worst thing in the world. People over 65 already spend a ton of money on healthcare, especially in the last 12 months of life. In the event we spend more money on the elderly what is the end goal? We have a bunch of people who aren’t working and live even longer for what purpose? Especially those who are sick and are living heavily impacted lives. I agree that people who have been working a long time should be rewarded with years of retirement, and that it is truly a matter of luck whether you get to experience those years, but I think it isnt the worst idea in the world for people who have amassed wealth in their life to have better resources for living longer than someone who hasn’t.; To tie a personal story into this. My mom was diagnosed with stage 4 breast cancer about 2 years ago. Shes been doing chemo to minimize and hold out for a vaccine to cure her cancer. Now I don’t actually know how much she is spending on this treatment, but she has amassed 7 figures at least in her 401k (which she can’t even access because shes not 58 or whatever age it is), and she still has money from selling her nice house and moving to Mississippi with my white ass family where cost of living is cheap. All of that is to say, she has had the luxury of fighting this cancer, despite her hating every second, because she made a solid money in her time. Its not like she had generational wealth, she grew up on a farm, and she was the first person in her family to go to graduate school. She just worked really hard to make money and provide for us, another reason why she was able to send me to JHU.; Now obviously nobody is saying that people who have a lot of money shouldnt be allowed to spend their money on their illnesses as an elderly adult. But we both know as people in medicine how expensive it is to get these clinical trials completed and develop the medicine.; I have been working heavily in medicine recently and have learned alot about the grueling process of doing research, developing a drug, and going through the steps of approval for that drug. Its expensive and labor intensive. That costs money, like a lot. So that money is either coming out of our pockets in taxes, or the elderly pockets. I do believe that we should continue spending as a society for the elderly to have care, but there is certainly risk in heavily democratizing care. Do we as a society really benefit from having a bunch of sick old people spending a bunch of money prolonging their life? Honestly, I dont think so. Everybody experiences the loss of their parents, I personally haven’t yet, but I know I will and that reality has been staring me in the face a while. I feel that spending all this money on elderly care just is not the best way forward and I dont see the benefit of spending much more on it. Now I certainly believe the system that needs the most revision is insurance, they make an exuberant amount of money, and this system should exist for people who are unlucky in their younger years and are threatened with the reality that they won’t make it to those retirement years. For people like my mom who have worked hard providing for me and my brother as a single mom and can’t access the 401k money she has saved, I would say insurance and spending exist for them. I understand I am biased and that this logic doesn’t exist for people who aren’t able to save enough money to really retire but that second point is a different story.; I am tired of typing this out I have other things to do, but I did want to provide my perspective, honestly not for you, but for me to be able to get my thoughts on a page and further develop a thought that was sneaking around in the back of my brain and I wanted to understand it.; Alright good luck with this study, and we should probably wish Landon luck because he is about to soend the day at wafflehouse. I will say though good for club basketball because unless he packed on hella weight since I last saw him, he needs it. | O14: Little or none | P14: Friends, my partner, money | Q14: Relationships & social life; Financial security | R14: Put extra effort into relationships, make a ton of money | S14: Social engagement; Financial planning | T14: Healthcare is the most important, AI this AI that whatever, just take viagra tbh; For me I build CNNs and so I care more about AI applications but the other logic is consistent. | U14: Personal relevance; Healthcare system & caregiving; Technology & AI | V14: I dont see healthcare changing so its worrying that I will get old and have these issues. I am excited to party with the boys in the retirement home 🎉 | W14: Healthcare system & caregiving; Financial security, work & basic needs
A15: G1-014 | B15: 1 | C15: 24 | D15: =Combined!G15 -> Student age (≤29) | E15: Female | F15: United States | G15: United States | H15: The age increasing in number (but != lack of health) | I15: Passage of time / getting older | J15: Loneliness | K15: Social connection & isolation | L15: Access to healthcare, because everyone deserves equitable healthcare | M15: Access, cost & equity; Healthcare system & caregiving | N15: Medicare has specific initiatives for dementia and other conditions which is good | O15: Names an action or idea | P15: Health, Energy, Community | Q15: Physical health & mobility; Relationships & social life | R15: Exercise regularly and eat healthy | S15: Healthy lifestyle & habits (general); Exercise & physical activity; Diet & nutrition | T15: There’s more money going into AI applications and longer reproductive health (IVF, etc) than general healthy aging | U15: Chronic disease & physical health; Financial security, work & basic needs; Technology & AI; Reproductive health & fertility | V15: AI/ML pervasively used in everything | W15: Technology & AI
A16: G1-015 | B16: 1 | C16: 23 | D16: =Combined!G16 -> Student age (≤29) | E16: Male | F16: United States | G16: United States | H16: Levels of Aura | I16: Other | J16: Health Care | K16: Healthcare system & caregiving | L16: Lack of health care | M16: Healthcare system & caregiving | N16: More Awareness | O16: Names an action or idea | P16: 1. Gym Gains; 2. Healthy body; 3. Mobility | Q16: Physical health & mobility | R16: Go to Gym | S16: Exercise & physical activity | T16: I care about myself rather than training ML models | U16: Personal relevance; Technology & AI | V16: The thing that excites me is my determination to get jacked and what scares me is aging | W16: Other
A17: G1-016 | B17: 1 | C17: 22 | D17: =Combined!G17 -> Student age (≤29) | E17: Male | F17: United States | G17: United States | H17: The growth and eventually biological deterioration of the human body and the mind over the course of time | I17: Decline & change in function; Biological / cellular process; Passage of time / getting older; Physical & bodily change; Cognitive & mental change; Growth, experience & wisdom | J17: Alzheimer’s and chronic illnesses | K17: Chronic disease & physical health; Cognitive decline & dementia | L17: Healthcare claims | M17: Healthcare system & caregiving | N17: Easier access to healthcare | O17: Names an action or idea | P17: memory family and health | Q17: Physical health & mobility; Memory & cognitive sharpness; Relationships & social life | R17: working out, focus on relationships and mindfulness | S17: Social engagement; Stress & emotional well-being | T17: Society vs personal different | U17: Personal relevance; Broad benefit to society | V17: Ai can work i have faith in precision medicine. Frightens is prolly ai too strong and sentient | W17: Technology & AI; Research, science & treatments; Prevention & early detection
... A76: G1-075 | B76: 1 | C76: 23 | D76: =Combined!G76 -> Student age (≤29) | E76: Female | F76: United States | G76: United States | H76: Being in 60s | I76: Passage of time / getting older | J76: Probably healthcare | K76: Healthcare system & caregiving | L76: Definitely affordable healthcare | M76: Access, cost & equity; Healthcare system & caregiving | N76: lower prescription drug costs and making long term care more affordable and accessible | O76: Names an action or idea | P76: My health, my wealth, my support system | Q76: Physical health & mobility; Financial security | R76: Preventative care, investment, and being involved with my community. | S76: Social engagement; Preventive & medical care; Financial planning | T76: I do think that accessibility of healthcare is the primary hindrance for healthcare in this country. I do think research is also equally important. AI can definitely help, but if it doesn't reach people to the extent required it won't be effective on a bigger scale | U76: All connected / equally important; Access, cost & equity; Healthcare system & caregiving; Technology & AI; Research, science & treatments | V76: I'm excited that people will be able to live longer and healthier lives but I constantly worry if the future is going to be hospitable in terms of wealth, the environment and healthcare options we are preparing for. | W76: Access, cost & equity; Healthcare system & caregiving; Longevity & lifespan; Population & societal burden
A77: G2-001 | B77: 2 | C77: 20 | D77: =Combined!G77 -> Student age (≤29) | E77: Male | F77: United States | G77: United States | H77: The process where the body slowly deteriorates due to ware in cells and genome | I77: Decline & change in function; Biological / cellular process; Physical & bodily change | J77: Issues with connecting to a rapidly changing social and professional environmen. | K77: Social connection & isolation | L77: I believe the insurance commuting elder fraud should be fixed as it is damaging and leaves elders very vulnerable. | M77: Access, cost & equity | N77: No | O77: Little or none | P77: Memory, connections, athleticism | Q77: Physical health & mobility; Memory & cognitive sharpness; Relationships & social life | R77: I excersizes to stay healthy and fit. | S77: Healthy lifestyle & habits (general); Exercise & physical activity | T77: I believe health is most important personally, but society values productiveness over personal health. | U77: Personal relevance; Broad benefit to society; Chronic disease & physical health; Ageism & how society treats older adults | Z77: Ensuring safe research when using human subjects | AA77: Safety, accuracy & misuse; Research, science & treatments
A78: G2-002 | B78: 2 | C78: 19 | D78: =Combined!G78 -> Student age (≤29) | E78: Male | F78: United States | G78: United States | H78: Your cells dying faster than they can be replaced | I78: Biological / cellular process | J78: Changing opinions | K78: Other | L78: Replacing the workforce, as an aging population's most immediate effects would be in the jobs they leave and the economic downturn. | M78: Financial security, work & basic needs; Population & societal burden | N78: No, if anything they are actively exacurbating up the issue | O78: Little or none | P78: Mental flexibility, ability to have fun, an able body | Q78: Physical health & mobility | R78: Not currently | S78: Not doing anything yet | T78: The third option wouldn't have as much of an impact without the other two already being accomplished, and the second option can indirectly induce the first option | U78: Broad benefit to society; All connected / equally important; Technology & AI | Z78: AI usage, immigration policy, reproductive rights, abortion | AA78: Technology & AI; Ethics, regulation & policy; Reproductive health & fertility
A79: G2-003 | B79: 2 | C79: 19 | D79: =Combined!G79 -> Student age (≤29) | E79: Female | F79: United States | G79: United States | H79: The progressive deterioration of bodily function with time and wear/tear - physically, mentally, and socially. | I79: Decline & change in function; Passage of time / getting older; Physical & bodily change; Cognitive & mental change; Social & role change | J79: Lack of social and financial infrastructure to support aging individuals - the retirement age keeps rising and I think it puts more stress on the elderly. | K79: Mental & emotional health; Social connection & isolation; Financial security, work & basic needs; Population & societal burden | L79: Access to healthy food and accessible exercise sources. Key because preventative/lifestyle medicine is the healthiest and most moderate intervention. | M79: Access, cost & equity; Chronic disease & physical health; Research, science & treatments; Prevention & early detection | N79: No | O79: Little or none | P79: Autonomy, Agility, Flexibility | Q79: Physical health & mobility; Independence | R79: Weightlifting, yoga, reading | S79: Exercise & physical activity; Learning & mental stimulation | T79: Because I believe that accessibility when developing medical innovation is very important. I also think ML and AI can help make precision care medicine more affordable for patients in the future. | U79: Access, cost & equity; Technology & AI; Research, science & treatments; Prevention & early detection | Z79: Patient anonymity when using ML solutions - especially to prevent insurance rates hiking (illegal). | AA79: Access, cost & equity; Technology & AI; Ethics, regulation & policy; Prevention & early detection
A80: G2-004 | B80: 2 | C80: 21 | D80: =Combined!G80 -> Student age (≤29) | E80: Female | F80: United States | G80: United States | H80: The natural course of growing old. | I80: Passage of time / getting older; Natural stage of life | J80: limited resources and lack of care | K80: Population & societal burden | L80: As the aging population is increasing rapidly over the years, there is not enough people nor resources to support them through the rapidly changing world, creating a gap between this population and the younger population. This should be prioritized to create a more cohesive society. | M80: Access, cost & equity; Population & societal burden | N80: Telehealth or AI assistants, community engagement activities | O80: Names an action or idea | P80: Health, friends, at least one hobby | Q80: Physical health & mobility; Relationships & social life; Hobbies, curiosity & purpose | R80: Exercise and healthy-ish diet, maintaining social connections, finding a hobby that I practice very often | S80: Healthy lifestyle & habits (general); Exercise & physical activity; Diet & nutrition; Social engagement | T80: I ranked ii first because no developed technology or solutions can help society without making it affordable and accessible for all. | U80: Broad benefit to society; Access, cost & equity; Technology & AI | Z80: Again as I mentioned, if technology is only available to some groups and not the others, this raises ethical concerns of separating groups based on their eligibility or whether they can afford to live longer. | AA80: Access, cost & equity; Technology & AI; Ethics, regulation & policy; Longevity & lifespan
A81: G2-005 | B81: 2 | C81: 21 | D81: =Combined!G81 -> Student age (≤29) | E81: Female | F81: United States | G81: United States | H81: Aging is | I81: Other | J81: Housing | K81: Financial security, work & basic needs | L81: Nursing homes are becoming more and more expensive, and thus out of reach for many retirees who need the help. Also, due to the general housing prices, home ownership is not easily obtainable for many adults, who end up renting and often do not have the space to take in their parents. | M81: Access, cost & equity; Healthcare system & caregiving; Financial security, work & basic needs; Privacy & data protection | N81: Not really | O81: Little or none | P81: General mental acuity, hair, good skin | Q81: Memory & cognitive sharpness; Appearance | R81: Skincare (sunscreen, lotions, no products with harsh chemical formulations, etc) | S81: Preventive & medical care | T81: From a societal standpoint, democratizing the process allows for more accessible solutions and thus contributes more to general stability. Simply boosting reproductive health and longevity only benefits those with the existing ability to pay and participate in the healthcare system, and a significant portion of individuals would not benefit. It is important to not overlook the significance of expanding care, especially when it is listed (at least in the US) as one of the top voter concerns for the past 10 years. | U81: Broad benefit to society; Access, cost & equity; Healthcare system & caregiving; Longevity & lifespan; Reproductive health & fertility | Z81: When developing solutions for longevity, reproductive health, and AI-driven healthcare, significant ethical considerations emerge around stakeholder power dynamics and equitable access. Because financial backing and institutional authority often skew decision-making toward clinicians, policymakers, and corporations while sidelining patients, it is important to guard against these sorts of injustice by making sure all stakeholders have a voice in the process and ensuring that patient-centric realities are not overridden by administrative efficiency. Additionally, combining machine learning with democratization efforts introduces critical challenges regarding healthspan inequality, especially in terms of algorithmic bias, data privacy and data autonomy, which require careful safeguards to ensure fairness and protect individual privacy across diverse and vulnerable populations. | AA81: Access, cost & equity; Healthcare system & caregiving; Financial security, work & basic needs; Independence & autonomy; Technology & AI; Privacy & data protection; Safety, accuracy & misuse; Ethics, regulation & policy; Longevity & lifespan; Reproductive health & fertility; Population & societal burden
A82: G2-006 | B82: 2 | C82: 21 | D82: =Combined!G82 -> Student age (≤29) | E82: Female | F82: United States | G82: United States | H82: endurance through the progression of time | I82: Passage of time / getting older | J82: loneliness | K82: Social connection & isolation | L82: better standard of living for ALL and not just those who can afford it. should be a priority because of wealth disparity issues | M82: Access, cost & equity | N82: no | O82: Little or none | P82: relationships, physical well-being, contentness | Q82: Physical health & mobility; Mental & emotional well-being; Relationships & social life | R82: investing in my retirement account and taking good care of myself | S82: Financial planning | T82: because i think we first need to do the most good for the most people, doesn’t matter if that is with or without ai | U82: Broad benefit to society; Technology & AI | Z82: so many ethical and legal concerns with the use of ai, especially as it pertains to our social relationships. risk of extreme dependence, model alignment, unethical training and deployment, etc | AA82: Social connection & isolation; Technology & AI; Safety, accuracy & misuse; Ethics, regulation & policy
A83: G2-007 | B83: 2 | C83: 20 | D83: =Combined!G83 -> Student age (≤29) | E83: Female | F83: United States | G83: United States | H83: To me, aging is the biological process of human maturation. | I83: Biological / cellular process; Growth, experience & wisdom | J83: Too large of a dependent population, not enough of an adult population to provide for elders. Also social isolation. | K83: Social connection & isolation; Population & societal burden | L83: Social Isolation is the most preventable and should be prioritized. | M83: Social connection & isolation; Prevention & early detection | N83: In theory there are volunteer programs. | O83: Names an action or idea | P83: Health, social life, passion. | Q83: Physical health & mobility; Relationships & social life; Hobbies, curiosity & purpose | R83: Keeping 10k steps a day and eating healthy(ish), maintaining social connections. | S83: Healthy lifestyle & habits (general); Diet & nutrition; Social engagement | T83: I think people are obsessed with all the ways AI can be applied to healthcare, and I think there’s been a rise in concern for reproductive health/vitality. I don’t think democratizing healthcare solutions will ever be a priority within private healthcare (Despite the good it would do). | U83: Access, cost & equity; Healthcare system & caregiving; Technology & AI; Privacy & data protection; Reproductive health & fertility | Z83: Privacy, AI hallucinations and discrimination, financial barriers, etc. | AA83: Financial security, work & basic needs; Technology & AI; Privacy & data protection; Ethics, regulation & policy
A84: G2-008 | B84: 2 | C84: 59 | D84: =Combined!G84 -> Middle-aged (30–64) | E84: Male | F84: Greece | G84: Greece | H84: lower endurance, less flexibility, slower responsiveness | I84: Decline & change in function | J84: Better health | K84: Chronic disease & physical health | L84: Solving the larger fraction of cancers, or at least offering a good life for the patients | M84: Chronic disease & physical health; Quality of life | N84: Yes, I hear and read that research is advancing in this | O84: Yes | P84: Hearing, flexibility, sexual arousal | Q84: Physical health & mobility | R84: Leading an active life, exercising, keeping my mind alert | S84: Exercise & physical activity | T84: Because public health is the utmost objective for society while well being is my personal aim | U84: Personal relevance; Broad benefit to society; Chronic disease & physical health | Z84: The obvious ethical questions on AI using our personal health data. | AA84: Chronic disease & physical health; Technology & AI; Privacy & data protection; Ethics, regulation & policy
A85: G2-009 | B85: 2 | C85: 43 | D85: =Combined!G85 -> Middle-aged (30–64) | E85: Male | F85: Greece | G85: Greece | H85: Slower recevery from injuries | I85: Decline & change in function | J85: mobility | K85: Chronic disease & physical health | L85: mobility | M85: Chronic disease & physical health | N85: No | O85: Little or none | P85: brain power, moving ability | Q85: Physical health & mobility; Memory & cognitive sharpness | R85: weights | S85: Exercise & physical activity | T85: Personal view | U85: Personal relevance | Z85: equal access | AA85: Access, cost & equity
A86: G2-010 | B86: 2 | C86: 60 | D86: =Combined!G86 -> Middle-aged (30–64) | E86: Male | F86: Greece | G86: Greece | H86: Searching for the energy to do things as opposed to have energy in abundance while young.. | I86: Physical & bodily change | J86: To manage to maintain their quality of life.. | K86: Quality of life | L86: The sense of community and friendship which can erode on various fronts surprisingly fast as we get older in the ‘old’ sense of the term… | M86: Social connection & isolation | N86: On the contrary, people get increasingly isolated… | O86: Names an action or idea | P86: Health, kinship and participation | Q86: Physical health & mobility | R86: Trying to maintain all three.. | S86: Healthy lifestyle & habits (general) | T86: My ‘feel’ for them.. | U86: Other | Z86: Those who are ‘left behind’.. | AA86: Ageism & how society treats older adults
A87: G2-011 | B87: 2 | C87: 70 | D87: =Combined!G87 -> Elderly (65+) | E87: Male | F87: Greece | G87: Greece | H87: It is wonderful aging. You are getting more wise. | I87: Growth, experience & wisdom | J87: Keep them happy and healthy | K87: Chronic disease & physical health | L87: Avoiding loneliness | M87: Social connection & isolation | N87: It works in smaller communities also through family unity | O87: Names an action or idea | P87: Physical health clear mind and communication | Q87: Physical health & mobility; Memory & cognitive sharpness | R87: Working although in retirement | S87: Financial planning | T87: Because it's more sentimental approach | U87: Other | Z87: mankind thinking over machine | AA87: Other
A88: G2-012 | B88: 2 | C88: 20 | D88: =Combined!G88 -> Student age (≤29) | E88: Female | F88: United States | G88: United States | H88: Aging is the process of becoming an older member of society, which also includes retirement from the job market and, increased health risks. | I88: Passage of time / getting older; Social & role change | J88: Loneliness, finding purpose in life, limited social security benefits | K88: Social connection & isolation; Financial security, work & basic needs; Quality of life | L88: Loneliness and limited social security must be addressed for the aging population as these are key determinants of health outcomes. | M88: Chronic disease & physical health; Social connection & isolation; Financial security, work & basic needs; Population & societal burden | N88: Not much action | O88: Little or none | P88: Empathy, humor, compassion | Q88: Mental & emotional well-being; Hobbies, curiosity & purpose; Values & identity | R88: Continually doing community service and sharing the importance of it with younger generations | S88: Social engagement | T88: Longevity and health solutions must be made available to everyone first before we can apply machine learning and AI in my opinion, however, society would likely tend to let AI solve the issues faster without regard to those who may not be able to benefit from AI/ tech based solutions. | U88: Broad benefit to society; Access, cost & equity; Chronic disease & physical health; Technology & AI; Longevity & lifespan | Z88: How to test if these interventions are actually viable in a group of aging individuals | AA88: Safety, accuracy & misuse
... A117: G2-041 | B117: 2 | C117: 48 | D117: =Combined!G117 -> Middle-aged (30–64) | E117: Male | F117: India | G117: United States | H117: I see aging as the gradual decline in the body's ability to recover, repair itself, and function as efficiently as it did when younger. The goal should be to slow that decline and remain healthy for as long as possible. | I117: Decline & change in function; Physical & bodily change | J117: Cognitive decline, healthcare burden, reduced mobility | K117: Healthcare system & caregiving; Chronic disease & physical health; Cognitive decline & dementia; Population & societal burden | L117: I think preventing chronic diseases should be one of our highest priorities. Conditions such as cardiovascular disease, diabetes, and dementia can greatly affect both lifespan and quality of life, so identifying risks earlier could have a major impact. | M117: Chronic disease & physical health; Cognitive decline & dementia; Safety, accuracy & misuse; Prevention & early detection; Longevity & lifespan; Quality of life | N117: Yes. AI-based diagnostic tools, and personalized medicine are increasingly being used to identify risks and intervene earlier. | O117: Yes | P117: Physical strength, cognitive ability, independence | Q117: Physical health & mobility; Memory & cognitive sharpness; Independence | R117: I plan to stay physically active, maintain a healthy weight and diet, monitor important health indicators, get regular checkups, and continue challenging myself mentally. | S117: Healthy lifestyle & habits (general); Not doing anything yet; Exercise & physical activity; Diet & nutrition; Learning & mental stimulation; Preventive & medical care | T117: For me, AI is especially interesting because earlier prediction and personalized prevention could change how we manage health as we age. For society, I put accessibility first because even the best technology has limited value if large parts of the population cannot benefit from it. | U117: Personal relevance; Broad benefit to society; Access, cost & equity; Chronic disease & physical health; Technology & AI; Prevention & early detection; Population & societal burden | Z117: Data privacy and security, accuracy of AI predictions, potential bias, informed consent, and making sure technology supports rather than replaces appropriate human medical judgment. | AA117: Technology & AI; Privacy & data protection; Safety, accuracy & misuse; Ethics, regulation & policy; Prevention & early detection
A118: G2-042 | B118: 2 | C118: 20 | D118: =Combined!G118 -> Student age (≤29) | E118: Female | F118: United States | G118: United States | H118: Aging is the deterioration of cells over time due to the shorting of telomeres every time a cell duplicates thus leading to aging | I118: Decline & change in function; Biological / cellular process; Passage of time / getting older | J118: Dementia, lack of care, STIs | K118: Cognitive decline & dementia | L118: Proper care for the elderly, as many nursing homes do not treat some with respect and dignity just because they are nearing the end of their life. | M118: Healthcare system & caregiving; Ageism & how society treats older adults | N118: Not really but I also haven’t been looking | O118: Little or none | P118: My memories, my physical capabilities, my ability to enjoy food | Q118: Physical health & mobility; Memory & cognitive sharpness; Mental & emotional well-being; Hobbies, curiosity & purpose | R118: Not currently | S118: Not doing anything yet | T118: I ranked them this way because I believe that the most beneficial thing for everyone is affordable healthcare as everyone has the right to live a healthy life and not choose between death or debt. I think application of ai would be good for society as sooner recognition of diseases that become deadly later on would save a lot of lives. | U118: Broad benefit to society; Access, cost & equity; Healthcare system & caregiving; Chronic disease & physical health; Cognitive decline & dementia; Technology & AI
A119: G2-043 | B119: 2 | C119: 58 | D119: =Combined!G119 -> Middle-aged (30–64) | E119: Male | F119: Switzerland | G119: Switzerland | H119: just the process of getting older! | I119: Passage of time / getting older | J119: financial risk related to longevity risk | K119: Financial security, work & basic needs; Safety, accuracy & misuse; Longevity & lifespan | L119: healthcare! | M119: Healthcare system & caregiving | N119: no | O119: Little or none | P119: good health (physical, mental, financial) | Q119: Physical health & mobility; Financial security | R119: working on it everyday | S119: Other | T119: best ranking | U119: Other | Z119: cost of healthcare | AA119: Access, cost & equity; Healthcare system & caregiving
A120: G2-044 | B120: 2 | C120: 76 | D120: =Combined!G120 -> Elderly (65+) | E120: Male | F120: United States | G120: United States | H120: losing capacities- right now physical- I have 3 chronic conditions: rheumatoid arthritis, bronchiectasis and kidney disease | I120: Decline & change in function; Physical & bodily change | J120: lack of family caregivers | K120: Healthcare system & caregiving; Social connection & isolation | L120: insufficient pool of health service workers for in home care | M120: Healthcare system & caregiving; Chronic disease & physical health | N120: No | O120: Little or none | P120: mobility, independence, mental acuity | Q120: Physical health & mobility; Memory & cognitive sharpness; Independence | R120: considering enrolling in Envisage, an independent living program providing support with guaranteed entrance to retirement home if needed.. enrolling in JCC & municipal exercise & physical training programs | S120: Exercise & physical activity; Financial planning | T120: The crucial issue for society lies in democratizing the benefits of AI & tech so that meaning and sustenance are preserved as labor loses most of its value. Having more of us living longer in meager degrading conditions is of little benefit. | U120: Broad benefit to society; Access, cost & equity; Technology & AI; Longevity & lifespan; Quality of life | Z120: See earlier answers- Our society is in the process of bi-furcating into .1% ownership of capital where the value of labor is tending toward zero. I don't find this acceptable and solving this social/economic problem is our most crucial challenge. Sure it would be great to live longer with less pain & disability but the primary challenge lies in adapting our society into something that supports meaningful lives under changing circumstances. | AA120: Chronic disease & physical health; Social connection & isolation; Financial security, work & basic needs; Privacy & data protection; Longevity & lifespan; Quality of life
A121: G2-045 | B121: 2 | C121: 22 | D121: =Combined!G121 -> Student age (≤29) | E121: Female | F121: United States | G121: United States | H121: Aging is defined as the process of becoming older and our bodies adapting accordingly in response with changes in efficiency and physiology. | I121: Biological / cellular process; Passage of time / getting older | J121: Healthcare | K121: Healthcare system & caregiving | L121: One prominent challenge our aging population faces is lack of resources in healthcare and retirement, which prevents many individuals from seeking care. | M121: Healthcare system & caregiving; Financial security, work & basic needs; Prevention & early detection; Population & societal burden | N121: There are many plans like Medicaid and senior healthcare benefits, but it’s not advocated fully and properly, and people still feel skeptical. | O121: Names an action or idea | P121: Faith, connections, health | Q121: Physical health & mobility; Relationships & social life; Values & identity | R121: Trying to practice them everyday or frequently | S121: Healthy lifestyle & habits (general) | T121: I ranked them in this order because it is vital to focus on reproductive health in individuals because that can begin as young as birth. It is a key component in bringing in the next generation to this world. | U121: Reproductive health & fertility | Z121: With the topic on AI, it is important to only have it as a base line and not fully rely on artificial intelligence to discover and explore. | AA121: Technology & AI; Research, science & treatments
A122: G2-046 | B122: 2 | C122: 21 | D122: =Combined!G122 -> Student age (≤29) | E122: Male | F122: United States | G122: United States | H122: The shortening of telomeres causing more of our cells to go into senescence | I122: Biological / cellular process | J122: Healthcare | K122: Healthcare system & caregiving | L122: Rather than the medical side, we need to focus on policy: affordable care homes that won't take everything someone has | M122: Access, cost & equity; Healthcare system & caregiving; Ethics, regulation & policy | N122: It has been addressed | O122: Yes | P122: Mentally facilities, movement, friendsho | Q122: Physical health & mobility; Memory & cognitive sharpness; Relationships & social life | R122: Staying healthy, social, and sleeping well | S122: Healthy lifestyle & habits (general); Sleep & rest; Social engagement | T122: I believe there is not enough of a focus for society to truly focus on reproductive health, but I find it hard to see how II can be prioritized without I. | U122: Broad benefit to society; Reproductive health & fertility | Z122: Data security, and insurance using the information to raise rates | AA122: Access, cost & equity; Privacy & data protection
A123: G2-047 | B123: 2 | C123: 26 | D123: =Combined!G123 -> Student age (≤29) | E123: Male | F123: United States | G123: United States | H123: Your body changing over time and your cells slowly breaking down | I123: Decline & change in function; Biological / cellular process; Passage of time / getting older; Physical & bodily change | J123: Ensuring we have good quality of life in addition to long life | K123: Quality of life | L123: How to extend quality of life . Because everyone wants to be able to see and run with their grand kids | M123: Access, cost & equity; Reproductive health & fertility; Quality of life | N123: Not as of now. But I'm sure with medical advancements theres some to come | O123: Names an action or idea | P123: Strength, memory and autonomy | Q123: Physical health & mobility; Memory & cognitive sharpness; Independence | R123: I am working out, eating a healthy diet and trying to read more | S123: Healthy lifestyle & habits (general); Diet & nutrition; Learning & mental stimulation | T123: I believe society has this order with there importance | U123: Broad benefit to society | Z123: Not using humans in unethical experiments | AA123: Ethics, regulation & policy; Research, science & treatments
